Workbook

Sheet Dashboard
B2: NICOBAR DESIGN PVT. LTD. · PURCHASE INVOICES FY 2026-27
B3: Expense Ledger – Dashboard | H3: As of | I3: =TODAY() -> 46298
B4: Live from the "Invoice Register" sheet – updates automatically when rows are added. Blue text = edit if needed.
B6: Invoice total | C6: Net payable (after TDS) | G6: GST charged (ITC) | H6: TDS to deduct | J6: RCM IGST payable
B7: =SUMIFS('Invoice Register'!$X$5:$X$2024,'Invoice Register'!$A$5:$A$2024,">0") -> 9266045.6 | C7: =SUMIFS('Invoice Register'!$Z$5:$Z$2024,'Invoice Register'!$A$5:$A$2024,">0") -> 8975814.6 | G7: =SUMIFS('Invoice Register'!$T$5:$T$2024,'Invoice Register'!$A$5:$A$2024,">0")+SUMIFS('Invoice Register'!$U$5:$U$2024,'Invoice Register'!$A$5:$A$2024,">0")+SUMIFS('Invoice Register'!$V$5:$V$2024,'Invoice Register'!$A$5:$A$2024,">0") -> 1115384.1 | H7: =SUMIFS('Invoice Register'!$Y$5:$Y$2024,'Invoice Register'!$A$5:$A$2024,">0") -> 290231 | J7: =ROUND(SUMIFS('Invoice Register'!$Q$5:$Q$2024,'Invoice Register'!$A$5:$A$2024,">0",'Invoice Register'!$AR$5:$AR$2024,"RCM*")*18%,0) -> 14100
B8: =SUMPRODUCT(('Invoice Register'!$C$5:$C$2024<>"")/COUNTIF('Invoice Register'!$C$5:$C$2024,'Invoice Register'!$C$5:$C$2024&"")) -> 72 | C8: =COUNTIFS('Invoice Register'!$A$5:$A$2024,">0") -> 117 | G8: Subject to GSTR-2B | H8: Confirm rates with CA | J8: 18% on import of services
B10: Spend by vendor | G10: Spend by invoice month
B11: Vendor (as in Supplier column) | C11: Invoice total | D11: Lines | E11: Share | G11: Month | H11: Invoice total | I11: Lines | J11: ₹ lakh
B12: Cushman & Wakefield India Private Limited | C12: =SUMIFS('Invoice Register'!$X$5:$X$2024,'Invoice Register'!$G$5:$G$2024,B12,'Invoice Register'!$A$5:$A$2024,">0") -> 1563500 | D12: =COUNTIFS('Invoice Register'!$G$5:$G$2024,B12,'Invoice Register'!$A$5:$A$2024,">0") -> 1 | E12: =IF($C$7=0,0,C12/$C$20) -> 0.16873433 | G12: 46113 | H12: =SUMIFS('Invoice Register'!$X$5:$X$2024,'Invoice Register'!$D$5:$D$2024,">="&G12,'Invoice Register'!$D$5:$D$2024,"<"&EDATE(G12,1),'Invoice Register'!$A$5:$A$2024,">0") -> 9383.51 | I12: =COUNTIFS('Invoice Register'!$D$5:$D$2024,">="&G12,'Invoice Register'!$D$5:$D$2024,"<"&EDATE(G12,1),'Invoice Register'!$A$5:$A$2024,">0") -> 2 | J12: =ROUND(H12/100000,2) -> 0.09
B13: DLF Home Developers Limited | C13: =SUMIFS('Invoice Register'!$X$5:$X$2024,'Invoice Register'!$G$5:$G$2024,B13,'Invoice Register'!$A$5:$A$2024,">0") -> 1482156.2 | D13: =COUNTIFS('Invoice Register'!$G$5:$G$2024,B13,'Invoice Register'!$A$5:$A$2024,">0") -> 14 | E13: =IF($C$7=0,0,C13/$C$20) -> 0.15995564 | G13: 46143 | H13: =SUMIFS('Invoice Register'!$X$5:$X$2024,'Invoice Register'!$D$5:$D$2024,">="&G13,'Invoice Register'!$D$5:$D$2024,"<"&EDATE(G13,1),'Invoice Register'!$A$5:$A$2024,">0") -> 583977.33 | I13: =COUNTIFS('Invoice Register'!$D$5:$D$2024,">="&G13,'Invoice Register'!$D$5:$D$2024,"<"&EDATE(G13,1),'Invoice Register'!$A$5:$A$2024,">0") -> 5 | J13: =ROUND(H13/100000,2) -> 5.84
B14: Antya Web Private Limited | C14: =SUMIFS('Invoice Register'!$X$5:$X$2024,'Invoice Register'!$G$5:$G$2024,B14,'Invoice Register'!$A$5:$A$2024,">0") -> 1416000 | D14: =COUNTIFS('Invoice Register'!$G$5:$G$2024,B14,'Invoice Register'!$A$5:$A$2024,">0") -> 1 | E14: =IF($C$7=0,0,C14/$C$20) -> 0.152816 | G14: 46174 | H14: =SUMIFS('Invoice Register'!$X$5:$X$2024,'Invoice Register'!$D$5:$D$2024,">="&G14,'Invoice Register'!$D$5:$D$2024,"<"&EDATE(G14,1),'Invoice Register'!$A$5:$A$2024,">0") -> 74288.08 | I14: =COUNTIFS('Invoice Register'!$D$5:$D$2024,">="&G14,'Invoice Register'!$D$5:$D$2024,"<"&EDATE(G14,1),'Invoice Register'!$A$5:$A$2024,">0") -> 3 | J14: =ROUND(H14/100000,2) -> 0.74
B15: M/s Stitch-9 | C15: =SUMIFS('Invoice Register'!$X$5:$X$2024,'Invoice Register'!$G$5:$G$2024,B15,'Invoice Register'!$A$5:$A$2024,">0") -> 1180590 | D15: =COUNTIFS('Invoice Register'!$G$5:$G$2024,B15,'Invoice Register'!$A$5:$A$2024,">0") -> 1 | E15: =IF($C$7=0,0,C15/$C$20) -> 0.12741034 | G15: 46204 | H15: =SUMIFS('Invoice Register'!$X$5:$X$2024,'Invoice Register'!$D$5:$D$2024,">="&G15,'Invoice Register'!$D$5:$D$2024,"<"&EDATE(G15,1),'Invoice Register'!$A$5:$A$2024,">0") -> 511872.28 | I15: =COUNTIFS('Invoice Register'!$D$5:$D$2024,">="&G15,'Invoice Register'!$D$5:$D$2024,"<"&EDATE(G15,1),'Invoice Register'!$A$5:$A$2024,">0") -> 6 | J15: =ROUND(H15/100000,2) -> 5.12
B16: Branch of Quang Vinh Ceramic Co., Ltd (Vietnam) | C16: =SUMIFS('Invoice Register'!$X$5:$X$2024,'Invoice Register'!$G$5:$G$2024,B16,'Invoice Register'!$A$5:$A$2024,">0") -> 1164340.8 | D16: =COUNTIFS('Invoice Register'!$G$5:$G$2024,B16,'Invoice Register'!$A$5:$A$2024,">0") -> 10 | E16: =IF($C$7=0,0,C16/$C$20) -> 0.12565671 | G16: 46235 | H16: =SUMIFS('Invoice Register'!$X$5:$X$2024,'Invoice Register'!$D$5:$D$2024,">="&G16,'Invoice Register'!$D$5:$D$2024,"<"&EDATE(G16,1),'Invoice Register'!$A$5:$A$2024,">0") -> 1308684.1 | I16: =COUNTIFS('Invoice Register'!$D$5:$D$2024,">="&G16,'Invoice Register'!$D$5:$D$2024,"<"&EDATE(G16,1),'Invoice Register'!$A$5:$A$2024,">0") -> 33 | J16: =ROUND(H16/100000,2) -> 13.09
B17: Clay Craft India Limited | C17: =SUMIFS('Invoice Register'!$X$5:$X$2024,'Invoice Register'!$G$5:$G$2024,B17,'Invoice Register'!$A$5:$A$2024,">0") -> 632596 | D17: =COUNTIFS('Invoice Register'!$G$5:$G$2024,B17,'Invoice Register'!$A$5:$A$2024,">0") -> 3 | E17: =IF($C$7=0,0,C17/$C$20) -> 0.068270331 | G17: 46266 | H17: =SUMIFS('Invoice Register'!$X$5:$X$2024,'Invoice Register'!$D$5:$D$2024,">="&G17,'Invoice Register'!$D$5:$D$2024,"<"&EDATE(G17,1),'Invoice Register'!$A$5:$A$2024,">0") -> 6588916.4 | I17: =COUNTIFS('Invoice Register'!$D$5:$D$2024,">="&G17,'Invoice Register'!$D$5:$D$2024,"<"&EDATE(G17,1),'Invoice Register'!$A$5:$A$2024,">0") -> 66 | J17: =ROUND(H17/100000,2) -> 65.89
B18: Jatin Gulabrai Parekh | C18: =SUMIFS('Invoice Register'!$X$5:$X$2024,'Invoice Register'!$G$5:$G$2024,B18,'Invoice Register'!$A$5:$A$2024,">0") -> 451443 | D18: =COUNTIFS('Invoice Register'!$G$5:$G$2024,B18,'Invoice Register'!$A$5:$A$2024,">0") -> 1 | E18: =IF($C$7=0,0,C18/$C$20) -> 0.048720136 | G18: 46296 | H18: =SUMIFS('Invoice Register'!$X$5:$X$2024,'Invoice Register'!$D$5:$D$2024,">="&G18,'Invoice Register'!$D$5:$D$2024,"<"&EDATE(G18,1),'Invoice Register'!$A$5:$A$2024,">0") -> 181844 | I18: =COUNTIFS('Invoice Register'!$D$5:$D$2024,">="&G18,'Invoice Register'!$D$5:$D$2024,"<"&EDATE(G18,1),'Invoice Register'!$A$5:$A$2024,">0") -> 1 | J18: =ROUND(H18/100000,2) -> 1.82
B19: Other / new vendors | C19: =B7-SUM(C12:C18) -> 1375419.6 | D19: =C8-SUM(D12:D18) -> 86 | E19: =IF(C20=0,0,C19/C20) -> 0.14843652 | G19: 46327 | H19: =SUMIFS('Invoice Register'!$X$5:$X$2024,'Invoice Register'!$D$5:$D$2024,">="&G19,'Invoice Register'!$D$5:$D$2024,"<"&EDATE(G19,1),'Invoice Register'!$A$5:$A$2024,">0") -> 0 | I19: =COUNTIFS('Invoice Register'!$D$5:$D$2024,">="&G19,'Invoice Register'!$D$5:$D$2024,"<"&EDATE(G19,1),'Invoice Register'!$A$5:$A$2024,">0") -> 0 | J19: =ROUND(H19/100000,2) -> 0
B20: Total | C20: =SUM(C12:C19) -> 9266045.6 | D20: =SUM(D12:D19) -> 117 | E20: =SUM(E12:E19) -> 1 | G20: 46357 | H20: =SUMIFS('Invoice Register'!$X$5:$X$2024,'Invoice Register'!$D$5:$D$2024,">="&G20,'Invoice Register'!$D$5:$D$2024,"<"&EDATE(G20,1),'Invoice Register'!$A$5:$A$2024,">0") -> 0 | I20: =COUNTIFS('Invoice Register'!$D$5:$D$2024,">="&G20,'Invoice Register'!$D$5:$D$2024,"<"&EDATE(G20,1),'Invoice Register'!$A$5:$A$2024,">0") -> 0 | J20: =ROUND(H20/100000,2) -> 0
B21: Top 7 vendors by spend (the routine refreshes this list). All others are in "Other / new vendors". | G21: 46388 | H21: =SUMIFS('Invoice Register'!$X$5:$X$2024,'Invoice Register'!$D$5:$D$2024,">="&G21,'Invoice Register'!$D$5:$D$2024,"<"&EDATE(G21,1),'Invoice Register'!$A$5:$A$2024,">0") -> 0 | I21: =COUNTIFS('Invoice Register'!$D$5:$D$2024,">="&G21,'Invoice Register'!$D$5:$D$2024,"<"&EDATE(G21,1),'Invoice Register'!$A$5:$A$2024,">0") -> 0 | J21: =ROUND(H21/100000,2) -> 0
G22: 46419 | H22: =SUMIFS('Invoice Register'!$X$5:$X$2024,'Invoice Register'!$D$5:$D$2024,">="&G22,'Invoice Register'!$D$5:$D$2024,"<"&EDATE(G22,1),'Invoice Register'!$A$5:$A$2024,">0") -> 0 | I22: =COUNTIFS('Invoice Register'!$D$5:$D$2024,">="&G22,'Invoice Register'!$D$5:$D$2024,"<"&EDATE(G22,1),'Invoice Register'!$A$5:$A$2024,">0") -> 0 | J22: =ROUND(H22/100000,2) -> 0
G23: 46447 | H23: =SUMIFS('Invoice Register'!$X$5:$X$2024,'Invoice Register'!$D$5:$D$2024,">="&G23,'Invoice Register'!$D$5:$D$2024,"<"&EDATE(G23,1),'Invoice Register'!$A$5:$A$2024,">0") -> 0 | I23: =COUNTIFS('Invoice Register'!$D$5:$D$2024,">="&G23,'Invoice Register'!$D$5:$D$2024,"<"&EDATE(G23,1),'Invoice Register'!$A$5:$A$2024,">0") -> 0 | J23: =ROUND(H23/100000,2) -> 0
G24: FY total | H24: =SUM(H12:H23) -> 9258965.6 | I24: =SUM(I12:I23) -> 116 | J24: =SUM(J12:J23) -> 92.59
G25: Before Apr-26 (prior FY) | H25: =B7-H24 -> 7080 | I25: =C8-I24 -> 1 | J25: =ROUND(H25/100000,2) -> 0.07
B27: Taxable value by GST treatment | G27: GST & TDS summary
B28: GST treatment | C28: Taxable value | D28: Lines | E28: Share | G28: Item | H28: Amount
B29: IGST | C29: =SUMIFS('Invoice Register'!$Q$5:$Q$2024,'Invoice Register'!$S$5:$S$2024,B29,'Invoice Register'!$A$5:$A$2024,">0") -> 2871602.6 | D29: =COUNTIFS('Invoice Register'!$S$5:$S$2024,B29,'Invoice Register'!$A$5:$A$2024,">0") -> 26 | E29: =IF($C$34=0,0,C29/$C$34) -> 0.35231533 | G29: IGST charged | H29: =SUMIFS('Invoice Register'!$T$5:$T$2024,'Invoice Register'!$A$5:$A$2024,">0") -> 438567.11
B30: CGST+SGST | C30: =SUMIFS('Invoice Register'!$Q$5:$Q$2024,'Invoice Register'!$S$5:$S$2024,B30,'Invoice Register'!$A$5:$A$2024,">0") -> 3802585.5 | D30: =COUNTIFS('Invoice Register'!$S$5:$S$2024,B30,'Invoice Register'!$A$5:$A$2024,">0") -> 60 | E30: =IF($C$34=0,0,C30/$C$34) -> 0.4665371 | G30: CGST charged | H30: =SUMIFS('Invoice Register'!$U$5:$U$2024,'Invoice Register'!$A$5:$A$2024,">0") -> 338408.52
B31: Import (no GST) | C31: =SUMIFS('Invoice Register'!$Q$5:$Q$2024,'Invoice Register'!$S$5:$S$2024,B31,'Invoice Register'!$A$5:$A$2024,">0") -> 1242671.8 | D31: =COUNTIFS('Invoice Register'!$S$5:$S$2024,B31,'Invoice Register'!$A$5:$A$2024,">0") -> 19 | E31: =IF($C$34=0,0,C31/$C$34) -> 0.15246272 | G31: SGST charged | H31: =SUMIFS('Invoice Register'!$V$5:$V$2024,'Invoice Register'!$A$5:$A$2024,">0") -> 338408.52
B32: No GST (unregistered) | C32: =SUMIFS('Invoice Register'!$Q$5:$Q$2024,'Invoice Register'!$S$5:$S$2024,B32,'Invoice Register'!$A$5:$A$2024,">0") -> 88000 | D32: =COUNTIFS('Invoice Register'!$S$5:$S$2024,B32,'Invoice Register'!$A$5:$A$2024,">0") -> 3 | E32: =IF($C$34=0,0,C32/$C$34) -> 0.010796671 | G32: Total GST (ITC) | H32: =SUM(H29:H31) -> 1115384.1
B33: Other | C33: =SUMIFS('Invoice Register'!$Q$5:$Q$2024,'Invoice Register'!$A$5:$A$2024,">0")-SUM(C29:C32) -> 145800.52 | D33: =C8-SUM(D29:D32) -> 9 | E33: =IF($C$34=0,0,C33/$C$34) -> 0.017888185 | G33: IGST payable under RCM | H33: =J7 -> 14100
B34: Total | C34: =SUM(C29:C33) -> 8150660.5 | D34: =SUM(D29:D33) -> 117 | E34: =SUM(E29:E33) -> 1 | G34: TDS to deduct | H34: =H7 -> 290231
G35: Net payable to vendors | H35: =C7 -> 8975814.6
G37: Check: vendor total = invoice total | H37: =IF(ABS(C20-B7)<1,"OK","MISMATCH") -> OK
B38: Charts
B57: Needs attention (as of 03-Oct-2026 – edit or clear when done)
B58: ACTION | C58: Attach the Gmail connector to the scheduled task "Auto-add new invoices to Expense Register" (daily 09:07 IST) – runs of 02 and 03 Oct could not read invoice@nicobar.com.
B59: ACTION | C59: 4 large emails (24–25 Sep, 12–28 MB) could not be downloaded – save their PDFs into D:\Claude_Sales\Expenses (see "Emails Not Scanned" tab).
B60: ACTION | C60: Fill Vendor Code, GL Code and GL Description in 3.Vendor_GL_Codes.xlsx – 116 of 117 lines have no Exps GL Code.
B61: PAY/CHECK | C61: Pay IGST under RCM on Anthropic imports via GSTR-3B (see J7), then claim ITC.
B62: REVIEW | C62: TDS 0.1% (194Q) is applied on Clay Craft and Stitch-9 although their notes say "only if FY purchases > ₹50 L" – confirm FY purchases and set TDS Rate to 0 if below.
B63: REVIEW | C63: Confirm TDS rates with CA (10% rent, 2% contract/brokerage, 10% professional fees).
B64: REVIEW | C64: FX: Quang Vinh at ₹95.8179/USD; Anthropic at RBI/FBIL rate per invoice date – replace with bank/customs rate if different.

Sheet Invoice Register
A1: Nicobar Design Pvt. Ltd. – Purchase Invoice Register
A2: Add one row per invoice line. Blue cells = inputs; black cells = formulas (Year, Month, Taxable Amount, IGST, CGST, SGST, Invoice Total, TDS Amount, Net Payable). Copy formulas down for new rows.
A4: S.No. | B4: Folder / File | C4: Invoice No. | D4: Invoice Date | E4: Year | F4: Month | G4: Supplier | H4: Supplier GSTIN | I4: Item Code | J4: Description | K4: HSN | L4: Boxes | M4: Quantity | N4: Unit | O4: Rate (₹) | P4: Discount (₹) | Q4: Taxable Amount (₹) | R4: GST Rate | S4: Tax Type | T4: IGST (₹) | U4: CGST (₹) | V4: SGST (₹) | W4: Round Off (₹) | X4: Invoice Total (₹) | Y4: TDS Amount (₹) | Z4: Net Payable (₹) | AA4: Location Code | AB4: Vendor GL Code | AC4: Exps GL Code | AD4: Supplier State | AE4: Buyer GSTIN | AF4: Place of Supply | AG4: Buyer PO No. | AH4: PO Date | AI4: Delivery Note No. | AJ4: Reference No. | AK4: IRN | AL4: Ack No. | AM4: Ack Date | AN4: E-Way Bill No. | AO4: Transporter | AP4: LR No. | AQ4: Vehicle No. | AR4: RCM / GST Compliance | AS4: TDS Section | AT4: TDS Rate
A5: 1 | B5: Clay Craft India Limited\MN-10076-26-27 12.09.26.pdf | C5: MN/10076/26-27 | D5: 46277 | E5: =YEAR(D5) -> 2026 | F5: =TEXT(D5,"mmm") -> Sep | G5: Clay Craft India Limited | H5: 08AAACC6866D1ZO | I5: FG002530 | J5: NB Chip & Dip Platter Madagascar 8 Pcs (NBI015086) | K5: 69120090 | L5: 103 | M5: 824 | N5: SET | O5: 624 | P5: 0 | Q5: =M5*O5-P5 -> 514176 | R5: 0.05 | S5: IGST | T5: =IF(S5="IGST",ROUND(Q5*R5,2),0) -> 25708.8 | U5: =IF(S5="CGST+SGST",ROUND(Q5*R5/2,2),0) -> 0 | V5: =U5 -> 0 | W5: 0.2 | X5: =Q5+T5+U5+V5+W5 -> 539885 | Y5: =ROUND(Q5*AT5,0) -> 514 | Z5: =X5-Y5 -> 539371 | AD5: Rajasthan (08) | AE5: 06AAFCN6567R1ZL | AF5: Haryana (06) | AG5: 26000000212 | AH5: 46150 | AI5: 10077 | AJ5: 10025 | AK5: ae7effee14e9c500367bd89f189cbbe82144949d40cf3289faf00e7361cb9127 | AL5: 172621162836331 | AM5: 2026-09-12 18:39 | AN5: 751669414036 | AO5: Shyam Cargo Movers | AP5: 12047 | AQ5: HR47H6099 | AR5: No RCM – forward charge; goods, IGST 5% charged by supplier. ITC eligible (check GSTR-2B). | AS5: Sec 393(1) – purchase of goods (old 194Q), code 1031. Apply only if FY purchases from this supplier > ₹50 L (on excess). | AT5: 0.001
A6: 2 | B6: Stitch-9\S9-26-27-274 18.09.26.pdf | C6: S9/26-27/274 | D6: 46283 | E6: =YEAR(D6) -> 2026 | F6: =TEXT(D6,"mmm") -> Sep | G6: M/s Stitch-9 | H6: 09AAOFS1968D2ZS | I6: D1451 | J6: Bash Jumpsuit - Silk Blend Loose Fit | K6: 62114290 | M6: 348 | N6: PCS | O6: 2875 | P6: 0 | Q6: =M6*O6-P6 -> 1000500 | R6: 0.18 | S6: IGST | T6: =IF(S6="IGST",ROUND(Q6*R6,2),0) -> 180090 | U6: =IF(S6="CGST+SGST",ROUND(Q6*R6/2,2),0) -> 0 | V6: =U6 -> 0 | W6: 0 | X6: =Q6+T6+U6+V6+W6 -> 1180590 | Y6: =ROUND(Q6*AT6,0) -> 1001 | Z6: =X6-Y6 -> 1179589 | AD6: Uttar Pradesh (09) | AE6: 06AAFCN6567R1ZL | AF6: Haryana (06) | AG6: PO26000001140 | AK6: 99777f8e7b31a4d9e186beec882f4fab746542a5f80f935acb61b37d3d74aa72 | AL6: 142621334812849 | AM6: 18-09-2026 | AN6: 451773976269 | AO6: Kamlesh Tempo Transport | AQ6: DL01LAH1554 | AR6: No RCM – invoice states Reverse Charge: N; goods, IGST 18% charged. ITC eligible (check GSTR-2B). | AS6: Sec 393(1) – purchase of goods (old 194Q), code 1031. Apply only if FY purchases from this supplier > ₹50 L (on excess). | AT6: 0.001
A7: 3 | B7: Quang Vinh Ceramic Co Ltd\06-26QV-NICOBAR 25.09.26.pdf | C7: 06/26QV-NICOBAR | D7: 46290 | E7: =YEAR(D7) -> 2026 | F7: =TEXT(D7,"mmm") -> Sep | G7: Branch of Quang Vinh Ceramic Co., Ltd (Vietnam) | I7: NBI023354 | J7: Ceramic Jug 14.5x8.5x23 cm | K7: 69120010 | M7: 200 | N7: PCE | O7: =10.1*95.8179 -> 967.76079 | P7: 0 | Q7: =M7*O7-P7 -> 193552.16 | R7: 0 | S7: Import (no GST) | T7: =IF(S7="IGST",ROUND(Q7*R7,2),0) -> 0 | U7: =IF(S7="CGST+SGST",ROUND(Q7*R7/2,2),0) -> 0 | V7: =U7 -> 0 | W7: 0 | X7: =Q7+T7+U7+V7+W7 -> 193552.16 | Y7: =ROUND(Q7*AT7,0) -> 0 | Z7: =X7-Y7 -> 193552.16 | AD7: Vietnam (Import) | AE7: 06AAFCN6567R1ZL | AF7: Haryana (06) | AG7: PO26000000358; PO26000000526; PO26000000609 | AJ7: PI NICO25; NICO26; NICO27 | AR7: Not RCM – import of goods: IGST + BCD paid to Customs on Bill of Entry; claim IGST ITC from BoE. | AS7: Not applicable – import of goods from non-resident, no income taxable in India (old 195 / 194Q N/A). | AT7: 0
A8: 4 | B8: Quang Vinh Ceramic Co Ltd\06-26QV-NICOBAR 25.09.26.pdf | C8: 06/26QV-NICOBAR | D8: 46290 | E8: =YEAR(D8) -> 2026 | F8: =TEXT(D8,"mmm") -> Sep | G8: Branch of Quang Vinh Ceramic Co., Ltd (Vietnam) | I8: NBI005679 | J8: Ceramic Plate 21x21.5x1.5 cm | K8: 69120010 | M8: 144 | N8: PCE | O8: =5.4*95.8179 -> 517.41666 | P8: 0 | Q8: =M8*O8-P8 -> 74507.999 | R8: 0 | S8: Import (no GST) | T8: =IF(S8="IGST",ROUND(Q8*R8,2),0) -> 0 | U8: =IF(S8="CGST+SGST",ROUND(Q8*R8/2,2),0) -> 0 | V8: =U8 -> 0 | W8: 0 | X8: =Q8+T8+U8+V8+W8 -> 74507.999 | Y8: =ROUND(Q8*AT8,0) -> 0 | Z8: =X8-Y8 -> 74507.999 | AD8: Vietnam (Import) | AE8: 06AAFCN6567R1ZL | AF8: Haryana (06) | AG8: PO26000000358; PO26000000526; PO26000000609 | AJ8: PI NICO25; NICO26; NICO27 | AR8: Not RCM – import of goods: IGST + BCD paid to Customs on Bill of Entry; claim IGST ITC from BoE. | AS8: Not applicable – import of goods from non-resident, no income taxable in India (old 195 / 194Q N/A). | AT8: 0
A9: 5 | B9: Quang Vinh Ceramic Co Ltd\06-26QV-NICOBAR 25.09.26.pdf | C9: 06/26QV-NICOBAR | D9: 46290 | E9: =YEAR(D9) -> 2026 | F9: =TEXT(D9,"mmm") -> Sep | G9: Branch of Quang Vinh Ceramic Co., Ltd (Vietnam) | I9: NBI005681 | J9: Ceramic Bowl 11x11.5x5 cm | K9: 69120010 | M9: 384 | N9: PCE | O9: =2.3*95.8179 -> 220.38117 | P9: 0 | Q9: =M9*O9-P9 -> 84626.369 | R9: 0 | S9: Import (no GST) | T9: =IF(S9="IGST",ROUND(Q9*R9,2),0) -> 0 | U9: =IF(S9="CGST+SGST",ROUND(Q9*R9/2,2),0) -> 0 | V9: =U9 -> 0 | W9: 0 | X9: =Q9+T9+U9+V9+W9 -> 84626.369 | Y9: =ROUND(Q9*AT9,0) -> 0 | Z9: =X9-Y9 -> 84626.369 | AD9: Vietnam (Import) | AE9: 06AAFCN6567R1ZL | AF9: Haryana (06) | AG9: PO26000000358; PO26000000526; PO26000000609 | AJ9: PI NICO25; NICO26; NICO27 | AR9: Not RCM – import of goods: IGST + BCD paid to Customs on Bill of Entry; claim IGST ITC from BoE. | AS9: Not applicable – import of goods from non-resident, no income taxable in India (old 195 / 194Q N/A). | AT9: 0
A10: 6 | B10: Quang Vinh Ceramic Co Ltd\06-26QV-NICOBAR 25.09.26.pdf | C10: 06/26QV-NICOBAR | D10: 46290 | E10: =YEAR(D10) -> 2026 | F10: =TEXT(D10,"mmm") -> Sep | G10: Branch of Quang Vinh Ceramic Co., Ltd (Vietnam) | I10: NBI005678 | J10: Ceramic Plate 27x26x1.5 cm | K10: 69120010 | M10: 304 | N10: PCE | O10: =6.5*95.8179 -> 622.81635 | P10: 0 | Q10: =M10*O10-P10 -> 189336.17 | R10: 0 | S10: Import (no GST) | T10: =IF(S10="IGST",ROUND(Q10*R10,2),0) -> 0 | U10: =IF(S10="CGST+SGST",ROUND(Q10*R10/2,2),0) -> 0 | V10: =U10 -> 0 | W10: 0 | X10: =Q10+T10+U10+V10+W10 -> 189336.17 | Y10: =ROUND(Q10*AT10,0) -> 0 | Z10: =X10-Y10 -> 189336.17 | AD10: Vietnam (Import) | AE10: 06AAFCN6567R1ZL | AF10: Haryana (06) | AG10: PO26000000358; PO26000000526; PO26000000609 | AJ10: PI NICO25; NICO26; NICO27 | AR10: Not RCM – import of goods: IGST + BCD paid to Customs on Bill of Entry; claim IGST ITC from BoE. | AS10: Not applicable – import of goods from non-resident, no income taxable in India (old 195 / 194Q N/A). | AT10: 0
A11: 7 | B11: Quang Vinh Ceramic Co Ltd\06-26QV-NICOBAR 25.09.26.pdf | C11: 06/26QV-NICOBAR | D11: 46290 | E11: =YEAR(D11) -> 2026 | F11: =TEXT(D11,"mmm") -> Sep | G11: Branch of Quang Vinh Ceramic Co., Ltd (Vietnam) | I11: NBI020668 | J11: Ceramic Bowl 10x9.5x3.5 cm | K11: 69120010 | M11: 432 | N11: PCE | O11: =1.6*95.8179 -> 153.30864 | P11: 0 | Q11: =M11*O11-P11 -> 66229.332 | R11: 0 | S11: Import (no GST) | T11: =IF(S11="IGST",ROUND(Q11*R11,2),0) -> 0 | U11: =IF(S11="CGST+SGST",ROUND(Q11*R11/2,2),0) -> 0 | V11: =U11 -> 0 | W11: 0 | X11: =Q11+T11+U11+V11+W11 -> 66229.332 | Y11: =ROUND(Q11*AT11,0) -> 0 | Z11: =X11-Y11 -> 66229.332 | AD11: Vietnam (Import) | AE11: 06AAFCN6567R1ZL | AF11: Haryana (06) | AG11: PO26000000358; PO26000000526; PO26000000609 | AJ11: PI NICO25; NICO26; NICO27 | AR11: Not RCM – import of goods: IGST + BCD paid to Customs on Bill of Entry; claim IGST ITC from BoE. | AS11: Not applicable – import of goods from non-resident, no income taxable in India (old 195 / 194Q N/A). | AT11: 0
A12: 8 | B12: Quang Vinh Ceramic Co Ltd\06-26QV-NICOBAR 25.09.26.pdf | C12: 06/26QV-NICOBAR | D12: 46290 | E12: =YEAR(D12) -> 2026 | F12: =TEXT(D12,"mmm") -> Sep | G12: Branch of Quang Vinh Ceramic Co., Ltd (Vietnam) | I12: NBI017691 | J12: Ceramic Plate 21x21.5x1.5 cm | K12: 69120010 | M12: 312 | N12: PCE | O12: =5.8*95.8179 -> 555.74382 | P12: 0 | Q12: =M12*O12-P12 -> 173392.07 | R12: 0 | S12: Import (no GST) | T12: =IF(S12="IGST",ROUND(Q12*R12,2),0) -> 0 | U12: =IF(S12="CGST+SGST",ROUND(Q12*R12/2,2),0) -> 0 | V12: =U12 -> 0 | W12: 0 | X12: =Q12+T12+U12+V12+W12 -> 173392.07 | Y12: =ROUND(Q12*AT12,0) -> 0 | Z12: =X12-Y12 -> 173392.07 | AD12: Vietnam (Import) | AE12: 06AAFCN6567R1ZL | AF12: Haryana (06) | AG12: PO26000000358; PO26000000526; PO26000000609 | AJ12: PI NICO25; NICO26; NICO27 | AR12: Not RCM – import of goods: IGST + BCD paid to Customs on Bill of Entry; claim IGST ITC from BoE. | AS12: Not applicable – import of goods from non-resident, no income taxable in India (old 195 / 194Q N/A). | AT12: 0
A13: 9 | B13: Quang Vinh Ceramic Co Ltd\06-26QV-NICOBAR 25.09.26.pdf | C13: 06/26QV-NICOBAR | D13: 46290 | E13: =YEAR(D13) -> 2026 | F13: =TEXT(D13,"mmm") -> Sep | G13: Branch of Quang Vinh Ceramic Co., Ltd (Vietnam) | I13: NBI017690 | J13: Ceramic Plate 21x21.5x1.5 cm | K13: 69120010 | M13: 216 | N13: PCE | O13: =5.8*95.8179 -> 555.74382 | P13: 0 | Q13: =M13*O13-P13 -> 120040.67 | R13: 0 | S13: Import (no GST) | T13: =IF(S13="IGST",ROUND(Q13*R13,2),0) -> 0 | U13: =IF(S13="CGST+SGST",ROUND(Q13*R13/2,2),0) -> 0 | V13: =U13 -> 0 | W13: 0 | X13: =Q13+T13+U13+V13+W13 -> 120040.67 | Y13: =ROUND(Q13*AT13,0) -> 0 | Z13: =X13-Y13 -> 120040.67 | AD13: Vietnam (Import) | AE13: 06AAFCN6567R1ZL | AF13: Haryana (06) | AG13: PO26000000358; PO26000000526; PO26000000609 | AJ13: PI NICO25; NICO26; NICO27 | AR13: Not RCM – import of goods: IGST + BCD paid to Customs on Bill of Entry; claim IGST ITC from BoE. | AS13: Not applicable – import of goods from non-resident, no income taxable in India (old 195 / 194Q N/A). | AT13: 0
A14: 10 | B14: Quang Vinh Ceramic Co Ltd\06-26QV-NICOBAR 25.09.26.pdf | C14: 06/26QV-NICOBAR | D14: 46290 | E14: =YEAR(D14) -> 2026 | F14: =TEXT(D14,"mmm") -> Sep | G14: Branch of Quang Vinh Ceramic Co., Ltd (Vietnam) | I14: NBI017689 | J14: Ceramic Plate 27x26x1.5 cm | K14: 69120010 | M14: 200 | N14: PCE | O14: =6.9*95.8179 -> 661.14351 | P14: 0 | Q14: =M14*O14-P14 -> 132228.7 | R14: 0 | S14: Import (no GST) | T14: =IF(S14="IGST",ROUND(Q14*R14,2),0) -> 0 | U14: =IF(S14="CGST+SGST",ROUND(Q14*R14/2,2),0) -> 0 | V14: =U14 -> 0 | W14: 0 | X14: =Q14+T14+U14+V14+W14 -> 132228.7 | Y14: =ROUND(Q14*AT14,0) -> 0 | Z14: =X14-Y14 -> 132228.7 | AD14: Vietnam (Import) | AE14: 06AAFCN6567R1ZL | AF14: Haryana (06) | AG14: PO26000000358; PO26000000526; PO26000000609 | AJ14: PI NICO25; NICO26; NICO27 | AR14: Not RCM – import of goods: IGST + BCD paid to Customs on Bill of Entry; claim IGST ITC from BoE. | AS14: Not applicable – import of goods from non-resident, no income taxable in India (old 195 / 194Q N/A). | AT14: 0
A15: 11 | B15: Quang Vinh Ceramic Co Ltd\06-26QV-NICOBAR 25.09.26.pdf | C15: 06/26QV-NICOBAR | D15: 46290 | E15: =YEAR(D15) -> 2026 | F15: =TEXT(D15,"mmm") -> Sep | G15: Branch of Quang Vinh Ceramic Co., Ltd (Vietnam) | I15: NBI023349 | J15: Ceramic Cup 13x10.2x10 cm | K15: 69120010 | M15: 256 | N15: PCE | O15: =3.95*95.8179 -> 378.48071 | P15: 0 | Q15: =M15*O15-P15 -> 96891.06 | R15: 0 | S15: Import (no GST) | T15: =IF(S15="IGST",ROUND(Q15*R15,2),0) -> 0 | U15: =IF(S15="CGST+SGST",ROUND(Q15*R15/2,2),0) -> 0 | V15: =U15 -> 0 | W15: 0 | X15: =Q15+T15+U15+V15+W15 -> 96891.06 | Y15: =ROUND(Q15*AT15,0) -> 0 | Z15: =X15-Y15 -> 96891.06 | AD15: Vietnam (Import) | AE15: 06AAFCN6567R1ZL | AF15: Haryana (06) | AG15: PO26000000358; PO26000000526; PO26000000609 | AJ15: PI NICO25; NICO26; NICO27 | AR15: Not RCM – import of goods: IGST + BCD paid to Customs on Bill of Entry; claim IGST ITC from BoE. | AS15: Not applicable – import of goods from non-resident, no income taxable in India (old 195 / 194Q N/A). | AT15: 0
A16: 12 | B16: Quang Vinh Ceramic Co Ltd\06-26QV-NICOBAR 25.09.26.pdf | C16: 06/26QV-NICOBAR | D16: 46290 | E16: =YEAR(D16) -> 2026 | F16: =TEXT(D16,"mmm") -> Sep | G16: Branch of Quang Vinh Ceramic Co., Ltd (Vietnam) | J16: Repacking Charge | M16: 1 | N16: LOT | O16: =350*95.8179 -> 33536.265 | P16: 0 | Q16: =M16*O16-P16 -> 33536.265 | R16: 0 | S16: Import (no GST) | T16: =IF(S16="IGST",ROUND(Q16*R16,2),0) -> 0 | U16: =IF(S16="CGST+SGST",ROUND(Q16*R16/2,2),0) -> 0 | V16: =U16 -> 0 | W16: 0 | X16: =Q16+T16+U16+V16+W16 -> 33536.265 | Y16: =ROUND(Q16*AT16,0) -> 0 | Z16: =X16-Y16 -> 33536.265 | AD16: Vietnam (Import) | AE16: 06AAFCN6567R1ZL | AF16: Haryana (06) | AG16: PO26000000358; PO26000000526; PO26000000609 | AJ16: PI NICO25; NICO26; NICO27 | AR16: Not RCM – import of goods: IGST + BCD paid to Customs on Bill of Entry; claim IGST ITC from BoE. | AS16: Not applicable – import of goods from non-resident, no income taxable in India (old 195 / 194Q N/A). | AT16: 0
A17: 13 | B17: Shreyas Gaikwad\S-09-01 15.09.26.pdf | C17: S#09/01 | D17: 46280 | E17: =YEAR(D17) -> 2026 | F17: =TEXT(D17,"mmm") -> Sep | G17: Shreyas Gaikwad | J17: Influencer Collaboration | M17: 1 | O17: 30000 | P17: 0 | Q17: =M17*O17-P17 -> 30000 | R17: 0 | S17: No GST (unregistered) | T17: =IF(S17="IGST",ROUND(Q17*R17,2),0) -> 0 | U17: =IF(S17="CGST+SGST",ROUND(Q17*R17/2,2),0) -> 0 | V17: =U17 -> 0 | W17: 0 | X17: =Q17+T17+U17+V17+W17 -> 30000 | Y17: =ROUND(Q17*AT17,0) -> 0 | Z17: =X17-Y17 -> 30000 | AE17: 07AAFCN6567R1ZJ | AF17: Delhi (07) | AR17: No RCM – unregistered individual; influencer/advertising service not notified under Sec 9(3)/9(4). No GST, no ITC. | AS17: Sec 393(1) – professional/advertising fees (old 194J), 10%, code 1027. Nil now: ₹30,000 is below ₹50,000 FY threshold; deduct 10% if FY total exceeds it. | AT17: 0
A18: 14 | B18: DPS Telecom (OPC) Private Limited\09-UPTIN26003027 23.09.26.pdf | C18: 09-UPTIN26003027 | D18: 46288 | E18: =YEAR(D18) -> 2026 | F18: =TEXT(D18,"mmm") -> Sep | G18: DPS Telecom (OPC) Private Limited | H18: 09AAFCD2760A1Z1 | J18: Internet Access Services – plan DPS-200MB-UL-3MN, 26/09/2026–25/12/2026 (Shop 272A, DLF Mall of India, Noida) | K18: 998422 | M18: 1 | N18: LOT | O18: 2847.46 | P18: 0 | Q18: =M18*O18-P18 -> 2847.46 | R18: 0.18 | S18: CGST+SGST | T18: =IF(S18="IGST",ROUND(Q18*R18,2),0) -> 0 | U18: =IF(S18="CGST+SGST",ROUND(Q18*R18/2,2),0) -> 256.27 | V18: =U18 -> 256.27 | W18: 0 | X18: =Q18+T18+U18+V18+W18 -> 3360 | Y18: =ROUND(Q18*AT18,0) -> 0 | Z18: =X18-Y18 -> 3360 | AD18: Uttar Pradesh (09) | AE18: 09AAFCN6567R1ZF | AF18: Uttar Pradesh (09) | AJ18: Customer ID DPS001879 | AR18: No RCM – forward charge; CGST 9% + SGST 9% charged by supplier (T&C "subject to reverse charge" line is boilerplate). ITC eligible against UP GSTIN (check GSTR-2B). | AS18: Sec 393(1) – contract/service (old 194C). Nil – ₹2,847 below single-payment threshold; review if FY total > ₹1 L. | AT18: 0
A19: 15 | B19: Vraj Commercial Private Limited\CH-0562-26-27 01.09.26.pdf | C19: CH/0562/26-27 | D19: 46266 | E19: =YEAR(D19) -> 2026 | F19: =TEXT(D19,"mmm") -> Sep | G19: Vraj Commercial Private Limited | H19: 22AAHCV7110N1Z8 | J19: CAM Charges for Sep-26 (Nicobar UG 26, Zora The Mall, Raipur) | K19: 998533 | M19: 2354 | N19: SQF | O19: 25 | P19: 0 | Q19: =M19*O19-P19 -> 58850 | R19: 0.18 | S19: CGST+SGST | T19: =IF(S19="IGST",ROUND(Q19*R19,2),0) -> 0 | U19: =IF(S19="CGST+SGST",ROUND(Q19*R19/2,2),0) -> 5296.5 | V19: =U19 -> 5296.5 | W19: 0 | X19: =Q19+T19+U19+V19+W19 -> 69443 | Y19: =ROUND(Q19*AT19,0) -> 1177 | Z19: =X19-Y19 -> 68266 | AD19: Chhattisgarh (22) | AE19: 22AAFCN6567R1ZR | AF19: Chhattisgarh (22) | AK19: 925b19d93bc7d631c6e68641135eb3ac2e3237db55bd5373b5baa3e915eed850 | AL19: 182623628025173 | AM19: 01-09-2026 | AR19: No RCM – forward charge; CGST 9% + SGST 9% charged. ITC eligible against CG GSTIN (check GSTR-2B). | AS19: Sec 393(1) – contract/service (old 194C), 2% (company). Confirm with CA. | AT19: 0.02
A20: 16 | B20: Vraj Commercial Private Limited\CH-0562-26-27 01.09.26.pdf | C20: CH/0562/26-27 | D20: 46266 | E20: =YEAR(D20) -> 2026 | F20: =TEXT(D20,"mmm") -> Sep | G20: Vraj Commercial Private Limited | H20: 22AAHCV7110N1Z8 | J20: HVAC Charges for Sep-26 (Nicobar UG 26, Zora The Mall, Raipur) | K20: 997319 | M20: 2354 | N20: SQF | O20: 10 | P20: 0 | Q20: =M20*O20-P20 -> 23540 | R20: 0.18 | S20: CGST+SGST | T20: =IF(S20="IGST",ROUND(Q20*R20,2),0) -> 0 | U20: =IF(S20="CGST+SGST",ROUND(Q20*R20/2,2),0) -> 2118.6 | V20: =U20 -> 2118.6 | W20: 0 | X20: =Q20+T20+U20+V20+W20 -> 27777.2 | Y20: =ROUND(Q20*AT20,0) -> 471 | Z20: =X20-Y20 -> 27306.2 | AD20: Chhattisgarh (22) | AE20: 22AAFCN6567R1ZR | AF20: Chhattisgarh (22) | AK20: 925b19d93bc7d631c6e68641135eb3ac2e3237db55bd5373b5baa3e915eed850 | AL20: 182623628025173 | AM20: 01-09-2026 | AR20: No RCM – forward charge; CGST 9% + SGST 9% charged. ITC eligible against CG GSTIN (check GSTR-2B). | AS20: Sec 393(1) – contract/service (old 194C), 2% (company). Confirm with CA. | AT20: 0.02
A21: 17 | B21: Vraj Commercial Private Limited\EL-DG-0545-26-27 02.09.26.pdf | C21: EL-DG/0545/26-27 | D21: 46267 | E21: =YEAR(D21) -> 2026 | F21: =TEXT(D21,"mmm") -> Sep | G21: Vraj Commercial Private Limited | H21: 22AAHCV7110N1Z8 | J21: Support Service to Electricity – Electricity Consumption Aug-26 – 1,428.30 UNT @ ₹13.50 (Opening 19197.4, Closing 20625.7) | K21: 998631 | M21: 1 | N21: LOT | O21: 19282 | P21: 0 | Q21: =M21*O21-P21 -> 19282 | R21: 0.18 | S21: CGST+SGST | T21: =IF(S21="IGST",ROUND(Q21*R21,2),0) -> 0 | U21: =IF(S21="CGST+SGST",ROUND(Q21*R21/2,2),0) -> 1735.38 | V21: =U21 -> 1735.38 | W21: 0 | X21: =Q21+T21+U21+V21+W21 -> 22752.76 | Y21: =ROUND(Q21*AT21,0) -> 386 | Z21: =X21-Y21 -> 22366.76 | AD21: Chhattisgarh (22) | AE21: 22AAFCN6567R1ZR | AF21: Chhattisgarh (22) | AK21: b323e2f2471536236b6c3b9b523a05bc7d63c88ce2ddc6756db926d4b6846fdc | AL21: 182623687389810 | AM21: 07-09-2026 | AR21: No RCM – forward charge; CGST 9% + SGST 9% charged on electricity support service. ITC eligible (check GSTR-2B). | AS21: Sec 393(1) – contract/service (old 194C), 2% (company). Confirm with CA whether electricity pass-through is excluded. | AT21: 0.02
A22: 18 | B22: Vraj Commercial Private Limited\EL-DG-0545-26-27 02.09.26.pdf | C22: EL-DG/0545/26-27 | D22: 46267 | E22: =YEAR(D22) -> 2026 | F22: =TEXT(D22,"mmm") -> Sep | G22: Vraj Commercial Private Limited | H22: 22AAHCV7110N1Z8 | J22: Support Service to Electricity – Electricity – MD Charges 18.01 KVA @ ₹400.00 | K22: 998631 | M22: 1 | N22: LOT | O22: 7204 | P22: 0 | Q22: =M22*O22-P22 -> 7204 | R22: 0.18 | S22: CGST+SGST | T22: =IF(S22="IGST",ROUND(Q22*R22,2),0) -> 0 | U22: =IF(S22="CGST+SGST",ROUND(Q22*R22/2,2),0) -> 648.36 | V22: =U22 -> 648.36 | W22: 0 | X22: =Q22+T22+U22+V22+W22 -> 8500.72 | Y22: =ROUND(Q22*AT22,0) -> 144 | Z22: =X22-Y22 -> 8356.72 | AD22: Chhattisgarh (22) | AE22: 22AAFCN6567R1ZR | AF22: Chhattisgarh (22) | AK22: b323e2f2471536236b6c3b9b523a05bc7d63c88ce2ddc6756db926d4b6846fdc | AL22: 182623687389810 | AM22: 07-09-2026 | AR22: No RCM – forward charge; CGST 9% + SGST 9% charged on electricity support service. ITC eligible (check GSTR-2B). | AS22: Sec 393(1) – contract/service (old 194C), 2% (company). Confirm with CA whether electricity pass-through is excluded. | AT22: 0.02
A23: 19 | B23: Vraj Commercial Private Limited\EL-DG-0545-26-27 02.09.26.pdf | C23: EL-DG/0545/26-27 | D23: 46267 | E23: =YEAR(D23) -> 2026 | F23: =TEXT(D23,"mmm") -> Sep | G23: Vraj Commercial Private Limited | H23: 22AAHCV7110N1Z8 | J23: Support Service to Electricity – DG Consumption Aug-26 – 9.24 UNT @ ₹33.77 | K23: 998631 | M23: 1 | N23: LOT | O23: 312 | P23: 0 | Q23: =M23*O23-P23 -> 312 | R23: 0.18 | S23: CGST+SGST | T23: =IF(S23="IGST",ROUND(Q23*R23,2),0) -> 0 | U23: =IF(S23="CGST+SGST",ROUND(Q23*R23/2,2),0) -> 28.08 | V23: =U23 -> 28.08 | W23: 0 | X23: =Q23+T23+U23+V23+W23 -> 368.16 | Y23: =ROUND(Q23*AT23,0) -> 6 | Z23: =X23-Y23 -> 362.16 | AD23: Chhattisgarh (22) | AE23: 22AAFCN6567R1ZR | AF23: Chhattisgarh (22) | AK23: b323e2f2471536236b6c3b9b523a05bc7d63c88ce2ddc6756db926d4b6846fdc | AL23: 182623687389810 | AM23: 07-09-2026 | AR23: No RCM – forward charge; CGST 9% + SGST 9% charged on electricity support service. ITC eligible (check GSTR-2B). | AS23: Sec 393(1) – contract/service (old 194C), 2% (company). Confirm with CA whether electricity pass-through is excluded. | AT23: 0.02
A24: 20 | B24: Vraj Commercial Private Limited\EL-DG-0545-26-27 02.09.26.pdf | C24: EL-DG/0545/26-27 | D24: 46267 | E24: =YEAR(D24) -> 2026 | F24: =TEXT(D24,"mmm") -> Sep | G24: Vraj Commercial Private Limited | H24: 22AAHCV7110N1Z8 | J24: Support Service to Electricity – Electricity Consumption Jul-26 Rate Diff – 1,479.20 UNT @ ₹1.28 | K24: 998631 | M24: 1 | N24: LOT | O24: 1893 | P24: 0 | Q24: =M24*O24-P24 -> 1893 | R24: 0.18 | S24: CGST+SGST | T24: =IF(S24="IGST",ROUND(Q24*R24,2),0) -> 0 | U24: =IF(S24="CGST+SGST",ROUND(Q24*R24/2,2),0) -> 170.37 | V24: =U24 -> 170.37 | W24: 0 | X24: =Q24+T24+U24+V24+W24 -> 2233.74 | Y24: =ROUND(Q24*AT24,0) -> 38 | Z24: =X24-Y24 -> 2195.74 | AD24: Chhattisgarh (22) | AE24: 22AAFCN6567R1ZR | AF24: Chhattisgarh (22) | AK24: b323e2f2471536236b6c3b9b523a05bc7d63c88ce2ddc6756db926d4b6846fdc | AL24: 182623687389810 | AM24: 07-09-2026 | AR24: No RCM – forward charge; CGST 9% + SGST 9% charged on electricity support service. ITC eligible (check GSTR-2B). | AS24: Sec 393(1) – contract/service (old 194C), 2% (company). Confirm with CA whether electricity pass-through is excluded. | AT24: 0.02
A25: 21 | B25: Vraj Commercial Private Limited\EL-DG-0545-26-27 02.09.26.pdf | C25: EL-DG/0545/26-27 | D25: 46267 | E25: =YEAR(D25) -> 2026 | F25: =TEXT(D25,"mmm") -> Sep | G25: Vraj Commercial Private Limited | H25: 22AAHCV7110N1Z8 | J25: Support Service to Electricity – Electricity – MD Charges Jul-26 Rate Diff – 18.01 KVA @ ₹24.99 | K25: 998631 | M25: 1 | N25: LOT | O25: 450 | P25: 0 | Q25: =M25*O25-P25 -> 450 | R25: 0.18 | S25: CGST+SGST | T25: =IF(S25="IGST",ROUND(Q25*R25,2),0) -> 0 | U25: =IF(S25="CGST+SGST",ROUND(Q25*R25/2,2),0) -> 40.5 | V25: =U25 -> 40.5 | W25: 0 | X25: =Q25+T25+U25+V25+W25 -> 531 | Y25: =ROUND(Q25*AT25,0) -> 9 | Z25: =X25-Y25 -> 522 | AD25: Chhattisgarh (22) | AE25: 22AAFCN6567R1ZR | AF25: Chhattisgarh (22) | AK25: b323e2f2471536236b6c3b9b523a05bc7d63c88ce2ddc6756db926d4b6846fdc | AL25: 182623687389810 | AM25: 07-09-2026 | AR25: No RCM – forward charge; CGST 9% + SGST 9% charged on electricity support service. ITC eligible (check GSTR-2B). | AS25: Sec 393(1) – contract/service (old 194C), 2% (company). Confirm with CA whether electricity pass-through is excluded. | AT25: 0.02
A26: 22 | B26: Vraj Commercial Private Limited\Rent-0613-26-27 12.09.26.pdf | C26: Rent/0613/26-27 | D26: 46277 | E26: =YEAR(D26) -> 2026 | F26: =TEXT(D26,"mmm") -> Sep | G26: Vraj Commercial Private Limited | H26: 22AAHCV7110N1Z8 | J26: Rental Services – 12% Pure Revenue Share on ₹8,40,218 for Aug-2026 (Zora The Mall, Raipur) | K26: 997212 | M26: 1 | N26: LOT | O26: 100826 | P26: 0 | Q26: =M26*O26-P26 -> 100826 | R26: 0.18 | S26: CGST+SGST | T26: =IF(S26="IGST",ROUND(Q26*R26,2),0) -> 0 | U26: =IF(S26="CGST+SGST",ROUND(Q26*R26/2,2),0) -> 9074.34 | V26: =U26 -> 9074.34 | W26: 0 | X26: =Q26+T26+U26+V26+W26 -> 118974.68 | Y26: =ROUND(Q26*AT26,0) -> 10083 | Z26: =X26-Y26 -> 108891.68 | AD26: Chhattisgarh (22) | AE26: 22AAFCN6567R1ZR | AF26: Chhattisgarh (22) | AK26: 8f5c80cdb0718df6b4c2b079ecef652f6659df643aafccf0686f7afb3a4dd8d7 | AL26: 182623774792279 | AM26: 15-09-2026 | AR26: No RCM – forward charge; CGST 9% + SGST 9% on rent. ITC eligible (check GSTR-2B). | AS26: Sec 393(1) – rent of land/building (old 194-I), 10%. | AT26: 0.1
A27: 23 | B27: Anthropic PBC\E87270F6-0001 22.04.26.pdf | C27: E87270F6-0001 | D27: 46134 | E27: =YEAR(D27) -> 2026 | F27: =TEXT(D27,"mmm") -> Apr | G27: Anthropic, PBC (USA) | J27: Claude API – one-time credit purchase (USD 10.00 @ ₹93.8351/USD) | M27: 1 | N27: NOS | O27: =10*93.8351 -> 938.351 | P27: 0 | Q27: =M27*O27-P27 -> 938.351 | R27: 0 | S27: Import (no GST) | T27: =IF(S27="IGST",ROUND(Q27*R27,2),0) -> 0 | U27: =IF(S27="CGST+SGST",ROUND(Q27*R27/2,2),0) -> 0 | V27: =U27 -> 0 | W27: 0 | X27: =Q27+T27+U27+V27+W27 -> 938.351 | Y27: =ROUND(Q27*AT27,0) -> 0 | Z27: =X27-Y27 -> 938.351 | AD27: USA (Import) | AE27: 07AAFCN6567R1ZJ | AF27: Delhi (07) | AJ27: Supplier India GST (OIDAR) 9924USA29003OSI | AR27: RCM – import of service; invoice says tax payable on reverse charge. Nicobar to pay IGST 18% on ₹ value via GSTR-3B and claim ITC. | AS27: Non-resident (old Sec 195) – no TDS if no PE in India / DTAA; confirm with CA (Form 15CA/CB for remittance). | AT27: 0
A28: 24 | B28: Anthropic PBC\E87270F6-0002 22.04.26.pdf | C28: E87270F6-0002 | D28: 46134 | E28: =YEAR(D28) -> 2026 | F28: =TEXT(D28,"mmm") -> Apr | G28: Anthropic, PBC (USA) | J28: Claude API – one-time credit purchase (USD 90.00 @ ₹93.8351/USD) | M28: 1 | N28: NOS | O28: =90*93.8351 -> 8445.159 | P28: 0 | Q28: =M28*O28-P28 -> 8445.159 | R28: 0 | S28: Import (no GST) | T28: =IF(S28="IGST",ROUND(Q28*R28,2),0) -> 0 | U28: =IF(S28="CGST+SGST",ROUND(Q28*R28/2,2),0) -> 0 | V28: =U28 -> 0 | W28: 0 | X28: =Q28+T28+U28+V28+W28 -> 8445.159 | Y28: =ROUND(Q28*AT28,0) -> 0 | Z28: =X28-Y28 -> 8445.159 | AD28: USA (Import) | AE28: 07AAFCN6567R1ZJ | AF28: Delhi (07) | AJ28: Supplier India GST (OIDAR) 9924USA29003OSI | AR28: RCM – import of service; invoice says tax payable on reverse charge. Nicobar to pay IGST 18% on ₹ value via GSTR-3B and claim ITC. | AS28: Non-resident (old Sec 195) – no TDS if no PE in India / DTAA; confirm with CA (Form 15CA/CB for remittance). | AT28: 0
A29: 25 | B29: Anthropic PBC\E87270F6-0003 20.05.26.pdf | C29: E87270F6-0003 | D29: 46162 | E29: =YEAR(D29) -> 2026 | F29: =TEXT(D29,"mmm") -> May | G29: Anthropic, PBC (USA) | J29: Claude API – one-time credit purchase (USD 200.00 @ ₹96.8441/USD) | M29: 1 | N29: NOS | O29: =200*96.8441 -> 19368.82 | P29: 0 | Q29: =M29*O29-P29 -> 19368.82 | R29: 0 | S29: Import (no GST) | T29: =IF(S29="IGST",ROUND(Q29*R29,2),0) -> 0 | U29: =IF(S29="CGST+SGST",ROUND(Q29*R29/2,2),0) -> 0 | V29: =U29 -> 0 | W29: 0 | X29: =Q29+T29+U29+V29+W29 -> 19368.82 | Y29: =ROUND(Q29*AT29,0) -> 0 | Z29: =X29-Y29 -> 19368.82 | AD29: USA (Import) | AE29: 07AAFCN6567R1ZJ | AF29: Delhi (07) | AJ29: Supplier India GST (OIDAR) 9924USA29003OSI | AR29: RCM – import of service; invoice says tax payable on reverse charge. Nicobar to pay IGST 18% on ₹ value via GSTR-3B and claim ITC. | AS29: Non-resident (old Sec 195) – no TDS if no PE in India / DTAA; confirm with CA (Form 15CA/CB for remittance). | AT29: 0
A30: 26 | B30: Anthropic PBC\E87270F6-0004 23.07.26.pdf | C30: E87270F6-0004 | D30: 46226 | E30: =YEAR(D30) -> 2026 | F30: =TEXT(D30,"mmm") -> Jul | G30: Anthropic, PBC (USA) | J30: Claude API – one-time credit purchase (USD 100.00 @ ₹96.5431/USD) | M30: 1 | N30: NOS | O30: =100*96.5431 -> 9654.31 | P30: 0 | Q30: =M30*O30-P30 -> 9654.31 | R30: 0 | S30: Import (no GST) | T30: =IF(S30="IGST",ROUND(Q30*R30,2),0) -> 0 | U30: =IF(S30="CGST+SGST",ROUND(Q30*R30/2,2),0) -> 0 | V30: =U30 -> 0 | W30: 0 | X30: =Q30+T30+U30+V30+W30 -> 9654.31 | Y30: =ROUND(Q30*AT30,0) -> 0 | Z30: =X30-Y30 -> 9654.31 | AD30: USA (Import) | AE30: 07AAFCN6567R1ZJ | AF30: Delhi (07) | AJ30: Supplier India GST (OIDAR) 9924USA29003OSI | AR30: RCM – import of service; invoice says tax payable on reverse charge. Nicobar to pay IGST 18% on ₹ value via GSTR-3B and claim ITC. | AS30: Non-resident (old Sec 195) – no TDS if no PE in India / DTAA; confirm with CA (Form 15CA/CB for remittance). | AT30: 0
A31: 27 | B31: Anthropic PBC\E87270F6-0005 30.07.26.pdf | C31: E87270F6-0005 | D31: 46233 | E31: =YEAR(D31) -> 2026 | F31: =TEXT(D31,"mmm") -> Jul | G31: Anthropic, PBC (USA) | J31: Claude API – one-time credit purchase (USD 100.00 @ ₹95.7327/USD) | K31: 998315 | M31: 1 | N31: NOS | O31: =100*95.7327 -> 9573.27 | P31: 0 | Q31: =M31*O31-P31 -> 9573.27 | R31: 0 | S31: Import (no GST) | T31: =IF(S31="IGST",ROUND(Q31*R31,2),0) -> 0 | U31: =IF(S31="CGST+SGST",ROUND(Q31*R31/2,2),0) -> 0 | V31: =U31 -> 0 | W31: 0 | X31: =Q31+T31+U31+V31+W31 -> 9573.27 | Y31: =ROUND(Q31*AT31,0) -> 0 | Z31: =X31-Y31 -> 9573.27 | AD31: USA (Import) | AE31: 07AAFCN6567R1ZJ | AF31: Delhi (07) | AJ31: Supplier India GST (OIDAR) 9924USA29003OSI | AR31: RCM – import of service; invoice says tax payable on reverse charge. Nicobar to pay IGST 18% on ₹ value via GSTR-3B and claim ITC. | AS31: Non-resident (old Sec 195) – no TDS if no PE in India / DTAA; confirm with CA (Form 15CA/CB for remittance). | AT31: 0
A32: 28 | B32: Anthropic PBC\E87270F6-0006 17.08.26.pdf | C32: E87270F6-0006 | D32: 46251 | E32: =YEAR(D32) -> 2026 | F32: =TEXT(D32,"mmm") -> Aug | G32: Anthropic, PBC (USA) | J32: Claude API – one-time credit purchase (USD 100.00 @ ₹95.6019/USD) | K32: 998315 | M32: 1 | N32: NOS | O32: =100*95.6019 -> 9560.19 | P32: 0 | Q32: =M32*O32-P32 -> 9560.19 | R32: 0 | S32: Import (no GST) | T32: =IF(S32="IGST",ROUND(Q32*R32,2),0) -> 0 | U32: =IF(S32="CGST+SGST",ROUND(Q32*R32/2,2),0) -> 0 | V32: =U32 -> 0 | W32: 0 | X32: =Q32+T32+U32+V32+W32 -> 9560.19 | Y32: =ROUND(Q32*AT32,0) -> 0 | Z32: =X32-Y32 -> 9560.19 | AD32: USA (Import) | AE32: 07AAFCN6567R1ZJ | AF32: Delhi (07) | AJ32: Supplier India GST (OIDAR) 9924USA29003OSI | AR32: RCM – import of service; invoice says tax payable on reverse charge. Nicobar to pay IGST 18% on ₹ value via GSTR-3B and claim ITC. | AS32: Non-resident (old Sec 195) – no TDS if no PE in India / DTAA; confirm with CA (Form 15CA/CB for remittance). | AT32: 0
A33: 29 | B33: Anthropic PBC\E87270F6-0007 02.09.26.pdf | C33: E87270F6-0007 | D33: 46267 | E33: =YEAR(D33) -> 2026 | F33: =TEXT(D33,"mmm") -> Sep | G33: Anthropic, PBC (USA) | J33: Claude API – one-time credit purchase (USD 20.00 @ ₹94.9701/USD) | K33: 998315 | M33: 1 | N33: NOS | O33: =20*94.9701 -> 1899.402 | P33: 0 | Q33: =M33*O33-P33 -> 1899.402 | R33: 0 | S33: Import (no GST) | T33: =IF(S33="IGST",ROUND(Q33*R33,2),0) -> 0 | U33: =IF(S33="CGST+SGST",ROUND(Q33*R33/2,2),0) -> 0 | V33: =U33 -> 0 | W33: 0 | X33: =Q33+T33+U33+V33+W33 -> 1899.402 | Y33: =ROUND(Q33*AT33,0) -> 0 | Z33: =X33-Y33 -> 1899.402 | AD33: USA (Import) | AE33: 07AAFCN6567R1ZJ | AF33: Delhi (07) | AJ33: Supplier India GST (OIDAR) 9924USA29003OSI | AR33: RCM – import of service; invoice says tax payable on reverse charge. Nicobar to pay IGST 18% on ₹ value via GSTR-3B and claim ITC. | AS33: Non-resident (old Sec 195) – no TDS if no PE in India / DTAA; confirm with CA (Form 15CA/CB for remittance). | AT33: 0
A34: 30 | B34: Anthropic PBC\E87270F6-0008 03.09.26.pdf | C34: E87270F6-0008 | D34: 46268 | E34: =YEAR(D34) -> 2026 | F34: =TEXT(D34,"mmm") -> Sep | G34: Anthropic, PBC (USA) | J34: Claude API – one-time credit purchase (USD 100.00 @ ₹94.4688/USD) | K34: 998315 | M34: 1 | N34: NOS | O34: =100*94.4688 -> 9446.88 | P34: 0 | Q34: =M34*O34-P34 -> 9446.88 | R34: 0 | S34: Import (no GST) | T34: =IF(S34="IGST",ROUND(Q34*R34,2),0) -> 0 | U34: =IF(S34="CGST+SGST",ROUND(Q34*R34/2,2),0) -> 0 | V34: =U34 -> 0 | W34: 0 | X34: =Q34+T34+U34+V34+W34 -> 9446.88 | Y34: =ROUND(Q34*AT34,0) -> 0 | Z34: =X34-Y34 -> 9446.88 | AD34: USA (Import) | AE34: 07AAFCN6567R1ZJ | AF34: Delhi (07) | AJ34: Supplier India GST (OIDAR) 9924USA29003OSI | AR34: RCM – import of service; invoice says tax payable on reverse charge. Nicobar to pay IGST 18% on ₹ value via GSTR-3B and claim ITC. | AS34: Non-resident (old Sec 195) – no TDS if no PE in India / DTAA; confirm with CA (Form 15CA/CB for remittance). | AT34: 0
A35: 31 | B35: Anthropic PBC\E87270F6-0009 07.09.26.pdf | C35: E87270F6-0009 | D35: 46272 | E35: =YEAR(D35) -> 2026 | F35: =TEXT(D35,"mmm") -> Sep | G35: Anthropic, PBC (USA) | J35: Claude API – one-time credit purchase (USD 100.00 @ ₹94.4467/USD) | K35: 998315 | M35: 1 | N35: NOS | O35: =100*94.4467 -> 9444.67 | P35: 0 | Q35: =M35*O35-P35 -> 9444.67 | R35: 0 | S35: Import (no GST) | T35: =IF(S35="IGST",ROUND(Q35*R35,2),0) -> 0 | U35: =IF(S35="CGST+SGST",ROUND(Q35*R35/2,2),0) -> 0 | V35: =U35 -> 0 | W35: 0 | X35: =Q35+T35+U35+V35+W35 -> 9444.67 | Y35: =ROUND(Q35*AT35,0) -> 0 | Z35: =X35-Y35 -> 9444.67 | AD35: USA (Import) | AE35: 07AAFCN6567R1ZJ | AF35: Delhi (07) | AJ35: Supplier India GST (OIDAR) 9924USA29003OSI | AR35: RCM – import of service; invoice says tax payable on reverse charge. Nicobar to pay IGST 18% on ₹ value via GSTR-3B and claim ITC. | AS35: Non-resident (old Sec 195) – no TDS if no PE in India / DTAA; confirm with CA (Form 15CA/CB for remittance). | AT35: 0
A36: 32 | B36: Antya Web Private Limited\TCAI-513-2627 12.09.26.pdf | C36: TCAI-513-2627 | D36: 46277 | E36: =YEAR(D36) -> 2026 | F36: =TEXT(D36,"mmm") -> Sep | G36: Antya Web Private Limited | H36: 33AAGCA7143R1ZA | J36: AI-Native Consulting to Nicobar – 1 month (12 Sep – 11 Oct 2026) | K36: 999293 | M36: 1 | N36: LOT | O36: 1200000 | P36: 0 | Q36: =M36*O36-P36 -> 1200000 | R36: 0.18 | S36: IGST | T36: =IF(S36="IGST",ROUND(Q36*R36,2),0) -> 216000 | U36: =IF(S36="CGST+SGST",ROUND(Q36*R36/2,2),0) -> 0 | V36: =U36 -> 0 | W36: 0 | X36: =Q36+T36+U36+V36+W36 -> 1416000 | Y36: =ROUND(Q36*AT36,0) -> 120000 | Z36: =X36-Y36 -> 1296000 | AD36: Tamil Nadu (33) | AE36: 07AAFCN6567R1ZJ | AF36: Delhi (07) | AR36: No RCM – forward charge; IGST 18% charged by supplier. ITC eligible (check GSTR-2B). MSME (UDYAM-TN-02-0471769) – pay within 45 days. Due date 16-09-2026. | AS36: Sec 393(1) – fees for professional/technical services (old 194J), 10%. Confirm with CA. | AT36: 0.1
A37: 33 | B37: Pine Labs Limited\INV092609248716 10.09.26.pdf | C37: INV092609248716 | D37: 46275 | E37: =YEAR(D37) -> 2026 | F37: =TEXT(D37,"mmm") -> Sep | G37: Pine Labs Limited | H37: 09AACCP7457K1ZV | J37: Plutus PoS Service Fee – Aug-26 (line 1) | K37: 998319 | M37: 1 | N37: NOS | O37: 1200 | P37: 0 | Q37: =M37*O37-P37 -> 1200 | R37: 0.18 | S37: IGST | T37: =IF(S37="IGST",ROUND(Q37*R37,2),0) -> 216 | U37: =IF(S37="CGST+SGST",ROUND(Q37*R37/2,2),0) -> 0 | V37: =U37 -> 0 | W37: 0 | X37: =Q37+T37+U37+V37+W37 -> 1416 | Y37: =ROUND(Q37*AT37,0) -> 24 | Z37: =X37-Y37 -> 1392 | AD37: Uttar Pradesh (09) | AE37: 07AAFCN6567R1ZJ | AF37: Delhi (07) | AG37: 12477167 | AH37: 45217 | AK37: 839bd782fcfc91fa31e6f83f9b07b14947d83dfd1799675967bc0255960a2c1d | AL37: 142621280907873 | AM37: 2026-09-11 10:55 | AR37: No RCM – forward charge; IGST 18% charged by supplier. ITC eligible (check GSTR-2B). Payment term 15 days. | AS37: Sec 393(1) – fees for technical services (old 194J(a)), 2%. Confirm with CA. | AT37: 0.02
A38: 34 | B38: Pine Labs Limited\INV092609248716 10.09.26.pdf | C38: INV092609248716 | D38: 46275 | E38: =YEAR(D38) -> 2026 | F38: =TEXT(D38,"mmm") -> Sep | G38: Pine Labs Limited | H38: 09AACCP7457K1ZV | J38: Plutus PoS Service Fee – Aug-26 (line 2) | K38: 998319 | M38: 1 | N38: NOS | O38: 4200 | P38: 0 | Q38: =M38*O38-P38 -> 4200 | R38: 0.18 | S38: IGST | T38: =IF(S38="IGST",ROUND(Q38*R38,2),0) -> 756 | U38: =IF(S38="CGST+SGST",ROUND(Q38*R38/2,2),0) -> 0 | V38: =U38 -> 0 | W38: 0 | X38: =Q38+T38+U38+V38+W38 -> 4956 | Y38: =ROUND(Q38*AT38,0) -> 84 | Z38: =X38-Y38 -> 4872 | AD38: Uttar Pradesh (09) | AE38: 07AAFCN6567R1ZJ | AF38: Delhi (07) | AG38: 12477167 | AH38: 45217 | AK38: 839bd782fcfc91fa31e6f83f9b07b14947d83dfd1799675967bc0255960a2c1d | AL38: 142621280907873 | AM38: 2026-09-11 10:55 | AR38: No RCM – forward charge; IGST 18% charged by supplier. ITC eligible (check GSTR-2B). Payment term 15 days. | AS38: Sec 393(1) – fees for technical services (old 194J(a)), 2%. Confirm with CA. | AT38: 0.02
A39: 35 | B39: Pine Labs Limited\INV092609248716 10.09.26.pdf | C39: INV092609248716 | D39: 46275 | E39: =YEAR(D39) -> 2026 | F39: =TEXT(D39,"mmm") -> Sep | G39: Pine Labs Limited | H39: 09AACCP7457K1ZV | J39: Plutus PoS Service Fee – Aug-26 (line 3) | K39: 998319 | M39: 1 | N39: NOS | O39: 600 | P39: 0 | Q39: =M39*O39-P39 -> 600 | R39: 0.18 | S39: IGST | T39: =IF(S39="IGST",ROUND(Q39*R39,2),0) -> 108 | U39: =IF(S39="CGST+SGST",ROUND(Q39*R39/2,2),0) -> 0 | V39: =U39 -> 0 | W39: 0 | X39: =Q39+T39+U39+V39+W39 -> 708 | Y39: =ROUND(Q39*AT39,0) -> 12 | Z39: =X39-Y39 -> 696 | AD39: Uttar Pradesh (09) | AE39: 07AAFCN6567R1ZJ | AF39: Delhi (07) | AG39: 12477167 | AH39: 45217 | AK39: 839bd782fcfc91fa31e6f83f9b07b14947d83dfd1799675967bc0255960a2c1d | AL39: 142621280907873 | AM39: 2026-09-11 10:55 | AR39: No RCM – forward charge; IGST 18% charged by supplier. ITC eligible (check GSTR-2B). Payment term 15 days. | AS39: Sec 393(1) – fees for technical services (old 194J(a)), 2%. Confirm with CA. | AT39: 0.02
A40: 36 | B40: Pine Labs Limited\INV092609248716 10.09.26.pdf | C40: INV092609248716 | D40: 46275 | E40: =YEAR(D40) -> 2026 | F40: =TEXT(D40,"mmm") -> Sep | G40: Pine Labs Limited | H40: 09AACCP7457K1ZV | J40: Plutus PoS Service Fee – Aug-26 (line 4) | K40: 998319 | M40: 1 | N40: NOS | O40: 600 | P40: 0 | Q40: =M40*O40-P40 -> 600 | R40: 0.18 | S40: IGST | T40: =IF(S40="IGST",ROUND(Q40*R40,2),0) -> 108 | U40: =IF(S40="CGST+SGST",ROUND(Q40*R40/2,2),0) -> 0 | V40: =U40 -> 0 | W40: 0 | X40: =Q40+T40+U40+V40+W40 -> 708 | Y40: =ROUND(Q40*AT40,0) -> 12 | Z40: =X40-Y40 -> 696 | AD40: Uttar Pradesh (09) | AE40: 07AAFCN6567R1ZJ | AF40: Delhi (07) | AG40: 12477167 | AH40: 45217 | AK40: 839bd782fcfc91fa31e6f83f9b07b14947d83dfd1799675967bc0255960a2c1d | AL40: 142621280907873 | AM40: 2026-09-11 10:55 | AR40: No RCM – forward charge; IGST 18% charged by supplier. ITC eligible (check GSTR-2B). Payment term 15 days. | AS40: Sec 393(1) – fees for technical services (old 194J(a)), 2%. Confirm with CA. | AT40: 0.02
A41: 37 | B41: Pine Labs Limited\INV092609248716 10.09.26.pdf | C41: INV092609248716 | D41: 46275 | E41: =YEAR(D41) -> 2026 | F41: =TEXT(D41,"mmm") -> Sep | G41: Pine Labs Limited | H41: 09AACCP7457K1ZV | J41: Plutus PoS Service Fee – Aug-26 (line 5) | K41: 998319 | M41: 1 | N41: NOS | O41: 2700 | P41: 0 | Q41: =M41*O41-P41 -> 2700 | R41: 0.18 | S41: IGST | T41: =IF(S41="IGST",ROUND(Q41*R41,2),0) -> 486 | U41: =IF(S41="CGST+SGST",ROUND(Q41*R41/2,2),0) -> 0 | V41: =U41 -> 0 | W41: 0 | X41: =Q41+T41+U41+V41+W41 -> 3186 | Y41: =ROUND(Q41*AT41,0) -> 54 | Z41: =X41-Y41 -> 3132 | AD41: Uttar Pradesh (09) | AE41: 07AAFCN6567R1ZJ | AF41: Delhi (07) | AG41: 12477167 | AH41: 45217 | AK41: 839bd782fcfc91fa31e6f83f9b07b14947d83dfd1799675967bc0255960a2c1d | AL41: 142621280907873 | AM41: 2026-09-11 10:55 | AR41: No RCM – forward charge; IGST 18% charged by supplier. ITC eligible (check GSTR-2B). Payment term 15 days. | AS41: Sec 393(1) – fees for technical services (old 194J(a)), 2%. Confirm with CA. | AT41: 0.02
A42: 38 | B42: Pine Labs Limited\INV092609248716 10.09.26.pdf | C42: INV092609248716 | D42: 46275 | E42: =YEAR(D42) -> 2026 | F42: =TEXT(D42,"mmm") -> Sep | G42: Pine Labs Limited | H42: 09AACCP7457K1ZV | J42: Plutus PoS Service Fee – Aug-26 (line 6) | K42: 998319 | M42: 1 | N42: NOS | O42: 1800 | P42: 0 | Q42: =M42*O42-P42 -> 1800 | R42: 0.18 | S42: IGST | T42: =IF(S42="IGST",ROUND(Q42*R42,2),0) -> 324 | U42: =IF(S42="CGST+SGST",ROUND(Q42*R42/2,2),0) -> 0 | V42: =U42 -> 0 | W42: 0 | X42: =Q42+T42+U42+V42+W42 -> 2124 | Y42: =ROUND(Q42*AT42,0) -> 36 | Z42: =X42-Y42 -> 2088 | AD42: Uttar Pradesh (09) | AE42: 07AAFCN6567R1ZJ | AF42: Delhi (07) | AG42: 12477167 | AH42: 45217 | AK42: 839bd782fcfc91fa31e6f83f9b07b14947d83dfd1799675967bc0255960a2c1d | AL42: 142621280907873 | AM42: 2026-09-11 10:55 | AR42: No RCM – forward charge; IGST 18% charged by supplier. ITC eligible (check GSTR-2B). Payment term 15 days. | AS42: Sec 393(1) – fees for technical services (old 194J(a)), 2%. Confirm with CA. | AT42: 0.02
A43: 39 | B43: Pine Labs Limited\INV092609248716 10.09.26.pdf | C43: INV092609248716 | D43: 46275 | E43: =YEAR(D43) -> 2026 | F43: =TEXT(D43,"mmm") -> Sep | G43: Pine Labs Limited | H43: 09AACCP7457K1ZV | J43: Plutus PoS Service Fee – Aug-26 (line 7) | K43: 998319 | M43: 1 | N43: NOS | O43: 9000 | P43: 0 | Q43: =M43*O43-P43 -> 9000 | R43: 0.18 | S43: IGST | T43: =IF(S43="IGST",ROUND(Q43*R43,2),0) -> 1620 | U43: =IF(S43="CGST+SGST",ROUND(Q43*R43/2,2),0) -> 0 | V43: =U43 -> 0 | W43: 0 | X43: =Q43+T43+U43+V43+W43 -> 10620 | Y43: =ROUND(Q43*AT43,0) -> 180 | Z43: =X43-Y43 -> 10440 | AD43: Uttar Pradesh (09) | AE43: 07AAFCN6567R1ZJ | AF43: Delhi (07) | AG43: 12477167 | AH43: 45217 | AK43: 839bd782fcfc91fa31e6f83f9b07b14947d83dfd1799675967bc0255960a2c1d | AL43: 142621280907873 | AM43: 2026-09-11 10:55 | AR43: No RCM – forward charge; IGST 18% charged by supplier. ITC eligible (check GSTR-2B). Payment term 15 days. | AS43: Sec 393(1) – fees for technical services (old 194J(a)), 2%. Confirm with CA. | AT43: 0.02
A44: 40 | B44: Pine Labs Limited\INV092609248716 10.09.26.pdf | C44: INV092609248716 | D44: 46275 | E44: =YEAR(D44) -> 2026 | F44: =TEXT(D44,"mmm") -> Sep | G44: Pine Labs Limited | H44: 09AACCP7457K1ZV | J44: Plutus PoS Service Fee – Aug-26 (line 8) | K44: 998319 | M44: 1 | N44: NOS | O44: 600 | P44: 0 | Q44: =M44*O44-P44 -> 600 | R44: 0.18 | S44: IGST | T44: =IF(S44="IGST",ROUND(Q44*R44,2),0) -> 108 | U44: =IF(S44="CGST+SGST",ROUND(Q44*R44/2,2),0) -> 0 | V44: =U44 -> 0 | W44: 0 | X44: =Q44+T44+U44+V44+W44 -> 708 | Y44: =ROUND(Q44*AT44,0) -> 12 | Z44: =X44-Y44 -> 696 | AD44: Uttar Pradesh (09) | AE44: 07AAFCN6567R1ZJ | AF44: Delhi (07) | AG44: 12477167 | AH44: 45217 | AK44: 839bd782fcfc91fa31e6f83f9b07b14947d83dfd1799675967bc0255960a2c1d | AL44: 142621280907873 | AM44: 2026-09-11 10:55 | AR44: No RCM – forward charge; IGST 18% charged by supplier. ITC eligible (check GSTR-2B). Payment term 15 days. | AS44: Sec 393(1) – fees for technical services (old 194J(a)), 2%. Confirm with CA. | AT44: 0.02
A45: 41 | B45: Pine Labs Limited\INV092609248716 10.09.26.pdf | C45: INV092609248716 | D45: 46275 | E45: =YEAR(D45) -> 2026 | F45: =TEXT(D45,"mmm") -> Sep | G45: Pine Labs Limited | H45: 09AACCP7457K1ZV | J45: Plutus PoS Service Fee – Aug-26 (line 9) | K45: 998319 | M45: 1 | N45: NOS | O45: 300 | P45: 0 | Q45: =M45*O45-P45 -> 300 | R45: 0.18 | S45: IGST | T45: =IF(S45="IGST",ROUND(Q45*R45,2),0) -> 54 | U45: =IF(S45="CGST+SGST",ROUND(Q45*R45/2,2),0) -> 0 | V45: =U45 -> 0 | W45: 0 | X45: =Q45+T45+U45+V45+W45 -> 354 | Y45: =ROUND(Q45*AT45,0) -> 6 | Z45: =X45-Y45 -> 348 | AD45: Uttar Pradesh (09) | AE45: 07AAFCN6567R1ZJ | AF45: Delhi (07) | AG45: 12477167 | AH45: 45217 | AK45: 839bd782fcfc91fa31e6f83f9b07b14947d83dfd1799675967bc0255960a2c1d | AL45: 142621280907873 | AM45: 2026-09-11 10:55 | AR45: No RCM – forward charge; IGST 18% charged by supplier. ITC eligible (check GSTR-2B). Payment term 15 days. | AS45: Sec 393(1) – fees for technical services (old 194J(a)), 2%. Confirm with CA. | AT45: 0.02
A46: 42 | B46: Pine Labs Limited\INV092609248716 10.09.26.pdf | C46: INV092609248716 | D46: 46275 | E46: =YEAR(D46) -> 2026 | F46: =TEXT(D46,"mmm") -> Sep | G46: Pine Labs Limited | H46: 09AACCP7457K1ZV | J46: Plutus PoS Service Fee – Aug-26 (line 10) | K46: 998319 | M46: 1 | N46: NOS | O46: 600 | P46: 0 | Q46: =M46*O46-P46 -> 600 | R46: 0.18 | S46: IGST | T46: =IF(S46="IGST",ROUND(Q46*R46,2),0) -> 108 | U46: =IF(S46="CGST+SGST",ROUND(Q46*R46/2,2),0) -> 0 | V46: =U46 -> 0 | W46: 0 | X46: =Q46+T46+U46+V46+W46 -> 708 | Y46: =ROUND(Q46*AT46,0) -> 12 | Z46: =X46-Y46 -> 696 | AD46: Uttar Pradesh (09) | AE46: 07AAFCN6567R1ZJ | AF46: Delhi (07) | AG46: 12477167 | AH46: 45217 | AK46: 839bd782fcfc91fa31e6f83f9b07b14947d83dfd1799675967bc0255960a2c1d | AL46: 142621280907873 | AM46: 2026-09-11 10:55 | AR46: No RCM – forward charge; IGST 18% charged by supplier. ITC eligible (check GSTR-2B). Payment term 15 days. | AS46: Sec 393(1) – fees for technical services (old 194J(a)), 2%. Confirm with CA. | AT46: 0.02
A47: 43 | B47: Pine Labs Limited\INV092609248716 10.09.26.pdf | C47: INV092609248716 | D47: 46275 | E47: =YEAR(D47) -> 2026 | F47: =TEXT(D47,"mmm") -> Sep | G47: Pine Labs Limited | H47: 09AACCP7457K1ZV | J47: Plutus PoS Service Fee – Aug-26 (line 11) | K47: 998319 | M47: 1 | N47: NOS | O47: 900 | P47: 0 | Q47: =M47*O47-P47 -> 900 | R47: 0.18 | S47: IGST | T47: =IF(S47="IGST",ROUND(Q47*R47,2),0) -> 162 | U47: =IF(S47="CGST+SGST",ROUND(Q47*R47/2,2),0) -> 0 | V47: =U47 -> 0 | W47: 0 | X47: =Q47+T47+U47+V47+W47 -> 1062 | Y47: =ROUND(Q47*AT47,0) -> 18 | Z47: =X47-Y47 -> 1044 | AD47: Uttar Pradesh (09) | AE47: 07AAFCN6567R1ZJ | AF47: Delhi (07) | AG47: 12477167 | AH47: 45217 | AK47: 839bd782fcfc91fa31e6f83f9b07b14947d83dfd1799675967bc0255960a2c1d | AL47: 142621280907873 | AM47: 2026-09-11 10:55 | AR47: No RCM – forward charge; IGST 18% charged by supplier. ITC eligible (check GSTR-2B). Payment term 15 days. | AS47: Sec 393(1) – fees for technical services (old 194J(a)), 2%. Confirm with CA. | AT47: 0.02
A48: 44 | B48: Trion Properties Private Limited\3652264407 09.09.26.pdf | C48: 3652264407 | D48: 46274 | E48: =YEAR(D48) -> 2026 | F48: =TEXT(D48,"mmm") -> Sep | G48: Trion Properties Private Limited | H48: 36AACCT3444Q1ZV | J48: L&L Agreement F-45 & F-46 – Recovery – Back Up Power Charges, 01-31 Aug 2026 | K48: 997221 | M48: 1 | N48: LOT | O48: 65 | P48: 0 | Q48: =M48*O48-P48 -> 65 | R48: 0.18 | S48: CGST+SGST | T48: =IF(S48="IGST",ROUND(Q48*R48,2),0) -> 0 | U48: =IF(S48="CGST+SGST",ROUND(Q48*R48/2,2),0) -> 5.85 | V48: =U48 -> 5.85 | W48: 0.3 | X48: =Q48+T48+U48+V48+W48 -> 77 | Y48: =ROUND(Q48*AT48,0) -> 1 | Z48: =X48-Y48 -> 76 | AD48: Telangana (36) | AE48: 36AAFCN6567R1ZI | AF48: Telangana (36) | AK48: cb522de0d722f65d0d17a6a9add7b2d76eeb85ce8516fb9006ec3f063c04e874 | AR48: No RCM – forward charge; CGST 9% + SGST 9% (rounded to rupee) charged by supplier. ITC eligible (check GSTR-2B). Interest @24% p.a. after due date 15-09-2026. | AS48: Sec 393(1) – contract/service (old 194C), 2% (company). Confirm with CA. | AT48: 0.02
A49: 45 | B49: Trion Properties Private Limited\3652264564 09.09.26.pdf | C49: 3652264564 | D49: 46274 | E49: =YEAR(D49) -> 2026 | F49: =TEXT(D49,"mmm") -> Sep | G49: Trion Properties Private Limited | H49: 36AACCT3444Q1ZV | J49: L&L Agreement F-45 & F-46 – Actual Chilled Water Charges, 01-31 Aug 2026 | K49: 997221 | M49: 1 | N49: LOT | O49: 11629 | P49: 0 | Q49: =M49*O49-P49 -> 11629 | R49: 0.18 | S49: CGST+SGST | T49: =IF(S49="IGST",ROUND(Q49*R49,2),0) -> 0 | U49: =IF(S49="CGST+SGST",ROUND(Q49*R49/2,2),0) -> 1046.61 | V49: =U49 -> 1046.61 | W49: 0.78 | X49: =Q49+T49+U49+V49+W49 -> 13723 | Y49: =ROUND(Q49*AT49,0) -> 233 | Z49: =X49-Y49 -> 13490 | AD49: Telangana (36) | AE49: 36AAFCN6567R1ZI | AF49: Telangana (36) | AK49: 6815884e9faa772a22fa86e54dfd2311ce08aae62ab0305d2e852e54f577d127 | AR49: No RCM – forward charge; CGST 9% + SGST 9% (rounded to rupee) charged by supplier. ITC eligible (check GSTR-2B). Interest @24% p.a. after due date 15-09-2026. | AS49: Sec 393(1) – contract/service (old 194C), 2% (company). Confirm with CA. | AT49: 0.02
A50: 46 | B50: Hansa Elite Luxe Interiors Pvt Ltd\GST-030-2026-27 31.08.26.pdf | C50: GST/030/2026-27 | D50: 46265 | E50: =YEAR(D50) -> 2026 | F50: =TEXT(D50,"mmm") -> Aug | G50: Hansa Elite Luxe Interiors Pvt Ltd | H50: 36AACCH6825M1Z8 | J50: Sharing of Security Guard – Charges for Aug-2026 | K50: 998525 | M50: 1 | N50: LOT | O50: 26667 | P50: 0 | Q50: =M50*O50-P50 -> 26667 | R50: 0.18 | S50: CGST+SGST | T50: =IF(S50="IGST",ROUND(Q50*R50,2),0) -> 0 | U50: =IF(S50="CGST+SGST",ROUND(Q50*R50/2,2),0) -> 2400.03 | V50: =U50 -> 2400.03 | W50: -0.06 | X50: =Q50+T50+U50+V50+W50 -> 31467 | Y50: =ROUND(Q50*AT50,0) -> 533 | Z50: =X50-Y50 -> 30934 | AD50: Telangana (36) | AE50: 36AAFCN6567R1ZI | AF50: Telangana (36) | AR50: No RCM – forward charge; CGST 9% + SGST 9% charged by supplier. ITC eligible (check GSTR-2B). | AS50: Sec 393(1) – contract/service (old 194C), 2% (company). Confirm with CA. | AT50: 0.02
A51: 47 | B51: Hansa Elite Luxe Interiors Pvt Ltd\008-2026-27 09.09.26.pdf | C51: 008/2026-27 | D51: 46274 | E51: =YEAR(D51) -> 2026 | F51: =TEXT(D51,"mmm") -> Sep | G51: Hansa Elite Luxe Interiors Pvt Ltd | H51: 36AACCH6825M1Z8 | J51: Debit Note – Monthly water HMWS (20% of ₹10,207) – Jul-26 | M51: 1 | N51: LOT | O51: 2041 | P51: 0 | Q51: =M51*O51-P51 -> 2041 | R51: 0 | S51: No GST (reimbursement) | T51: =IF(S51="IGST",ROUND(Q51*R51,2),0) -> 0 | U51: =IF(S51="CGST+SGST",ROUND(Q51*R51/2,2),0) -> 0 | V51: =U51 -> 0 | W51: 0 | X51: =Q51+T51+U51+V51+W51 -> 2041 | Y51: =ROUND(Q51*AT51,0) -> 0 | Z51: =X51-Y51 -> 2041 | AD51: Telangana (36) | AF51: Telangana (36) | AJ51: Debit Note (reimbursement) | AR51: Debit note for reimbursement of maintenance expenses – no GST charged, no ITC. Confirm with CA whether GST should apply. | AS51: Reimbursement of actual expenses – TDS generally not applicable; confirm with CA. | AT51: 0
A52: 48 | B52: Hansa Elite Luxe Interiors Pvt Ltd\008-2026-27 09.09.26.pdf | C52: 008/2026-27 | D52: 46274 | E52: =YEAR(D52) -> 2026 | F52: =TEXT(D52,"mmm") -> Sep | G52: Hansa Elite Luxe Interiors Pvt Ltd | H52: 36AACCH6825M1Z8 | J52: Debit Note – Additional water tankers 61 nos (20% of ₹90,900) – Jul-26 | M52: 1 | N52: LOT | O52: 18180 | P52: 0 | Q52: =M52*O52-P52 -> 18180 | R52: 0 | S52: No GST (reimbursement) | T52: =IF(S52="IGST",ROUND(Q52*R52,2),0) -> 0 | U52: =IF(S52="CGST+SGST",ROUND(Q52*R52/2,2),0) -> 0 | V52: =U52 -> 0 | W52: 0 | X52: =Q52+T52+U52+V52+W52 -> 18180 | Y52: =ROUND(Q52*AT52,0) -> 0 | Z52: =X52-Y52 -> 18180 | AD52: Telangana (36) | AF52: Telangana (36) | AJ52: Debit Note (reimbursement) | AR52: Debit note for reimbursement of maintenance expenses – no GST charged, no ITC. Confirm with CA whether GST should apply. | AS52: Reimbursement of actual expenses – TDS generally not applicable; confirm with CA. | AT52: 0
A53: 49 | B53: Hansa Elite Luxe Interiors Pvt Ltd\008-2026-27 09.09.26.pdf | C53: 008/2026-27 | D53: 46274 | E53: =YEAR(D53) -> 2026 | F53: =TEXT(D53,"mmm") -> Sep | G53: Hansa Elite Luxe Interiors Pvt Ltd | H53: 36AACCH6825M1Z8 | J53: Debit Note – Electricity common area sharing 142 units @ ₹11.49 – Jul-26 | M53: 1 | N53: LOT | O53: 1632 | P53: 0 | Q53: =M53*O53-P53 -> 1632 | R53: 0 | S53: No GST (reimbursement) | T53: =IF(S53="IGST",ROUND(Q53*R53,2),0) -> 0 | U53: =IF(S53="CGST+SGST",ROUND(Q53*R53/2,2),0) -> 0 | V53: =U53 -> 0 | W53: 0 | X53: =Q53+T53+U53+V53+W53 -> 1632 | Y53: =ROUND(Q53*AT53,0) -> 0 | Z53: =X53-Y53 -> 1632 | AD53: Telangana (36) | AF53: Telangana (36) | AJ53: Debit Note (reimbursement) | AR53: Debit note for reimbursement of maintenance expenses – no GST charged, no ITC. Confirm with CA whether GST should apply. | AS53: Reimbursement of actual expenses – TDS generally not applicable; confirm with CA. | AT53: 0
A54: 50 | B54: Hansa Elite Luxe Interiors Pvt Ltd\008-2026-27 09.09.26.pdf | C54: 008/2026-27 | D54: 46274 | E54: =YEAR(D54) -> 2026 | F54: =TEXT(D54,"mmm") -> Sep | G54: Hansa Elite Luxe Interiors Pvt Ltd | H54: 36AACCH6825M1Z8 | J54: Debit Note – Outside housekeeping sharing (₹12,000 / 3) – Jul-26 | M54: 1 | N54: LOT | O54: 4000 | P54: 0 | Q54: =M54*O54-P54 -> 4000 | R54: 0 | S54: No GST (reimbursement) | T54: =IF(S54="IGST",ROUND(Q54*R54,2),0) -> 0 | U54: =IF(S54="CGST+SGST",ROUND(Q54*R54/2,2),0) -> 0 | V54: =U54 -> 0 | W54: -1 | X54: =Q54+T54+U54+V54+W54 -> 3999 | Y54: =ROUND(Q54*AT54,0) -> 0 | Z54: =X54-Y54 -> 3999 | AD54: Telangana (36) | AF54: Telangana (36) | AJ54: Debit Note (reimbursement) | AR54: Debit note for reimbursement of maintenance expenses – no GST charged, no ITC. Confirm with CA whether GST should apply. | AS54: Reimbursement of actual expenses – TDS generally not applicable; confirm with CA. | AT54: 0
A55: 51 | B55: Jatin Gulabrai Parekh\2026-27-05-013 02.05.26.pdf | C55: 2026-27/05/013 | D55: 46144 | E55: =YEAR(D55) -> 2026 | F55: =TEXT(D55,"mmm") -> May | G55: Jatin Gulabrai Parekh | H55: 24AACPP9141M1ZF | J55: Society Maintenance – G12 One42, period 01-04-2026 to 31-03-2027 | K55: 997212 | M55: 1 | N55: LOT | O55: 382579 | P55: 0 | Q55: =M55*O55-P55 -> 382579 | R55: 0.18 | S55: CGST+SGST | T55: =IF(S55="IGST",ROUND(Q55*R55,2),0) -> 0 | U55: =IF(S55="CGST+SGST",ROUND(Q55*R55/2,2),0) -> 34432.11 | V55: =U55 -> 34432.11 | W55: -0.22 | X55: =Q55+T55+U55+V55+W55 -> 451443 | Y55: =ROUND(Q55*AT55,0) -> 7652 | Z55: =X55-Y55 -> 443791 | AD55: Gujarat (24) | AE55: 24AAFCN6567R5ZJ | AF55: Gujarat (24) | AK55: 7b9eef44cfc105630ffdf378c86f6ed0861ff5a52270084a8452397f8a6ea6ff | AL55: 162624488443866 | AM55: 2026-05-02 | AR55: No RCM – forward charge; CGST 9% + SGST 9% charged by supplier. ITC eligible (check GSTR-2B). | AS55: Sec 393(1) – contract/service (old 194C), 2% (company). Confirm with CA. | AT55: 0.02
A56: 52 | B56: Shyam Spectra IT Services Private Limited\EHRI001161-25-26 01.03.26.pdf | C56: EHRI001161/25-26 | D56: 46082 | E56: =YEAR(D56) -> 2026 | F56: =TEXT(D56,"mmm") -> Mar | G56: Shyam Spectra IT Services Private Limited | H56: 06AARCS7860A1Z5 | J56: AIVIS CCTV – Camera Health Monitoring, 1 Mar – 31 May 2026 (quarterly advance) | K56: 998713 | M56: 1 | N56: LOT | O56: 6000 | P56: 0 | Q56: =M56*O56-P56 -> 6000 | R56: 0.18 | S56: IGST | T56: =IF(S56="IGST",ROUND(Q56*R56,2),0) -> 1080 | U56: =IF(S56="CGST+SGST",ROUND(Q56*R56/2,2),0) -> 0 | V56: =U56 -> 0 | W56: 0 | X56: =Q56+T56+U56+V56+W56 -> 7080 | Y56: =ROUND(Q56*AT56,0) -> 120 | Z56: =X56-Y56 -> 6960 | AD56: Haryana (06) | AE56: 24AAFCN6567R5ZJ | AF56: Gujarat (24) | AJ56: CAN 603223 | AK56: 7b5e03b8eb5f5498a8d248250dd1e8a94624d2f658a7ef4bd965aacfca72b7c2 | AR56: No RCM – forward charge; IGST 18% charged by supplier. ITC eligible (check GSTR-2B). Bill also shows previous balance ₹21,240 unpaid (not included here). Invoice is FY 2025-26. | AS56: Sec 393(1) – contract/service (old 194C), 2% (company). Confirm with CA. | AT56: 0.02
A57: 53 | B57: Bharti Airtel Limited\MF2707I006723461 03.09.26.pdf | C57: MF2707I006723461 | D57: 46268 | E57: =YEAR(D57) -> 2026 | F57: =TEXT(D57,"mmm") -> Sep | G57: Bharti Airtel Limited | H57: 07AAACB2894G1ZP | J57: Mobile rentals – 29 connections, 02-Aug to 01-Sep-2026 | K57: 998413 | M57: 1 | N57: LOT | O57: 9821 | P57: 0 | Q57: =M57*O57-P57 -> 9821 | R57: 0.18 | S57: CGST+SGST | T57: =IF(S57="IGST",ROUND(Q57*R57,2),0) -> 0 | U57: =IF(S57="CGST+SGST",ROUND(Q57*R57/2,2),0) -> 883.89 | V57: =U57 -> 883.89 | W57: 0 | X57: =Q57+T57+U57+V57+W57 -> 11588.78 | Y57: =ROUND(Q57*AT57,0) -> 0 | Z57: =X57-Y57 -> 11588.78 | AD57: Delhi (07) | AE57: 07AAFCN6567R1ZJ | AF57: Delhi (07) | AJ57: Rel. no 1384739873 | AK57: fa6e4a37ad56e8cd9dc6275558030873fbd3d8e439e9648beb9fdfbfe77aa383 | AR57: No RCM – forward charge; CGST 9% + SGST 9% charged by supplier. ITC eligible (check GSTR-2B). Pay by 21-09-2026. | AS57: Generally no TDS on telecom bills paid to telecom operators; confirm with CA. | AT57: 0
A58: 54 | B58: Bharti Airtel Limited\MF2707I006723461 03.09.26.pdf | C58: MF2707I006723461 | D58: 46268 | E58: =YEAR(D58) -> 2026 | F58: =TEXT(D58,"mmm") -> Sep | G58: Bharti Airtel Limited | H58: 07AAACB2894G1ZP | J58: Late payment charges for Aug-2026 | K58: 999799 | M58: 1 | N58: LOT | O58: 100 | P58: 0 | Q58: =M58*O58-P58 -> 100 | R58: 0.18 | S58: CGST+SGST | T58: =IF(S58="IGST",ROUND(Q58*R58,2),0) -> 0 | U58: =IF(S58="CGST+SGST",ROUND(Q58*R58/2,2),0) -> 9 | V58: =U58 -> 9 | W58: 0 | X58: =Q58+T58+U58+V58+W58 -> 118 | Y58: =ROUND(Q58*AT58,0) -> 0 | Z58: =X58-Y58 -> 118 | AD58: Delhi (07) | AE58: 07AAFCN6567R1ZJ | AF58: Delhi (07) | AJ58: Rel. no 1384739873 | AK58: fa6e4a37ad56e8cd9dc6275558030873fbd3d8e439e9648beb9fdfbfe77aa383 | AR58: No RCM – forward charge; CGST 9% + SGST 9% charged by supplier. ITC eligible (check GSTR-2B). Pay by 21-09-2026. | AS58: Generally no TDS on telecom bills paid to telecom operators; confirm with CA. | AT58: 0
A59: 55 | B59: Vodafone Idea Limited\DLSO030926765967 03.09.26.pdf | C59: DLSO030926765967 | D59: 46268 | E59: =YEAR(D59) -> 2026 | F59: =TEXT(D59,"mmm") -> Sep | G59: Vodafone Idea Limited | H59: 07AAACB2100P1ZZ | J59: Mobile services 03-Aug to 02-Sep-2026 – 8 connections summary, pre-tax charges per account summary | K59: 998413 | M59: 1 | N59: LOT | O59: 30472.58 | P59: 0 | Q59: =M59*O59-P59 -> 30472.58 | R59: 0.18 | S59: CGST+SGST | T59: =IF(S59="IGST",ROUND(Q59*R59,2),0) -> 0 | U59: =IF(S59="CGST+SGST",ROUND(Q59*R59/2,2),0) -> 2742.53 | V59: =U59 -> 2742.53 | W59: 0 | X59: =Q59+T59+U59+V59+W59 -> 35957.64 | Y59: =ROUND(Q59*AT59,0) -> 0 | Z59: =X59-Y59 -> 35957.64 | AD59: Delhi (07) | AE59: 07AAFCN6567R1ZJ | AF59: Delhi (07) | AJ59: Cust no 163196736 | AK59: 68ae1de810028f8623239d1c5e39b6d04fb55b42f5fa579134319598986bb792 | AR59: No RCM – forward charge; CGST 9% + SGST 9% charged by supplier. ITC eligible (check GSTR-2B). Due 13-09-2026. | AS59: Generally no TDS on telecom bills paid to telecom operators; confirm with CA. | AT59: 0
A60: 56 | B60: Blue Dart Express Limited\2026806R00002349 31.08.26.pdf | C60: 2026806R00002349 | D60: 46265 | E60: =YEAR(D60) -> 2026 | F60: =TEXT(D60,"mmm") -> Aug | G60: Blue Dart Express Limited | H60: 06AAACB0446L1ZW | J60: Courier – Etail Air COD – Aug-26 (freight+VAS 7,863.66, IDC 1,783.36, EFSS 303.78, fuel 6,049.59, CAF 2,736.06) | K60: 996812 | M60: 1 | N60: LOT | O60: 18736.45 | P60: 0 | Q60: =M60*O60-P60 -> 18736.45 | R60: 0.18 | S60: CGST+SGST | T60: =IF(S60="IGST",ROUND(Q60*R60,2),0) -> 0 | U60: =IF(S60="CGST+SGST",ROUND(Q60*R60/2,2),0) -> 1686.28 | V60: =U60 -> 1686.28 | W60: 0 | X60: =Q60+T60+U60+V60+W60 -> 22109.01 | Y60: =ROUND(Q60*AT60,0) -> 375 | Z60: =X60-Y60 -> 21734.01 | AD60: Haryana (06) | AE60: 06AAFCN6567R1ZL | AF60: Haryana (06) | AJ60: A/c FAR322055 | AK60: 1ea85e08e93d98fd9d6bc4e59ead2825e106a407bdd75cb990b2965ef24746f3 | AR60: No RCM – invoice states RCM Applicable: N; CGST 9% + SGST 9% charged. ITC eligible (check GSTR-2B). Interest 2% p.m. on delay. | AS60: Sec 393(1) – contract/service (old 194C), 2% (company). Confirm with CA. | AT60: 0.02
A61: 57 | B61: Blue Dart Express Limited\2026806R00002350 31.08.26.pdf | C61: 2026806R00002350 | D61: 46265 | E61: =YEAR(D61) -> 2026 | F61: =TEXT(D61,"mmm") -> Aug | G61: Blue Dart Express Limited | H61: 06AAACB0446L1ZW | J61: Courier – Etail Air Prepaid – Aug-26 | K61: 996812 | M61: 1 | N61: LOT | O61: 14775.25 | P61: 0 | Q61: =M61*O61-P61 -> 14775.25 | R61: 0.18 | S61: CGST+SGST | T61: =IF(S61="IGST",ROUND(Q61*R61,2),0) -> 0 | U61: =IF(S61="CGST+SGST",ROUND(Q61*R61/2,2),0) -> 1329.77 | V61: =U61 -> 1329.77 | W61: 0 | X61: =Q61+T61+U61+V61+W61 -> 17434.79 | Y61: =ROUND(Q61*AT61,0) -> 296 | Z61: =X61-Y61 -> 17138.79 | AD61: Haryana (06) | AE61: 06AAFCN6567R1ZL | AF61: Haryana (06) | AJ61: A/c FAR322055 | AK61: e849e99c932cae11b221d5d985ca59d400d28133a217d8ba9bd4e0205a5977cf | AR61: No RCM – invoice states RCM Applicable: N; CGST 9% + SGST 9% charged. ITC eligible (check GSTR-2B). Interest 2% p.m. on delay. | AS61: Sec 393(1) – contract/service (old 194C), 2% (company). Confirm with CA. | AT61: 0.02
A62: 58 | B62: Blue Dart Express Limited\2026806R00002351 31.08.26.pdf | C62: 2026806R00002351 | D62: 46265 | E62: =YEAR(D62) -> 2026 | F62: =TEXT(D62,"mmm") -> Aug | G62: Blue Dart Express Limited | H62: 06AAACB0446L1ZW | J62: Courier – Domestic Priority – Aug-26 | K62: 996812 | M62: 1 | N62: LOT | O62: 6569.85 | P62: 0 | Q62: =M62*O62-P62 -> 6569.85 | R62: 0.18 | S62: CGST+SGST | T62: =IF(S62="IGST",ROUND(Q62*R62,2),0) -> 0 | U62: =IF(S62="CGST+SGST",ROUND(Q62*R62/2,2),0) -> 591.29 | V62: =U62 -> 591.29 | W62: 0 | X62: =Q62+T62+U62+V62+W62 -> 7752.43 | Y62: =ROUND(Q62*AT62,0) -> 131 | Z62: =X62-Y62 -> 7621.43 | AD62: Haryana (06) | AE62: 06AAFCN6567R1ZL | AF62: Haryana (06) | AJ62: A/c FAR322055 | AK62: 658744ff8fac597356a89960c7ff2e405846e2744e465e821aa17d9a4b7ab36b | AR62: No RCM – invoice states RCM Applicable: N; CGST 9% + SGST 9% charged. ITC eligible (check GSTR-2B). Interest 2% p.m. on delay. | AS62: Sec 393(1) – contract/service (old 194C), 2% (company). Confirm with CA. | AT62: 0.02
A63: 59 | B63: Blue Dart Express Limited\2026822R00000752 31.08.26.pdf | C63: 2026822R00000752 | D63: 46265 | E63: =YEAR(D63) -> 2026 | F63: =TEXT(D63,"mmm") -> Aug | G63: Blue Dart Express Limited | H63: 22AAACB0446L1Z2 | J63: Courier – Domestic Priority – Aug-26 | K63: 996812 | M63: 1 | N63: LOT | O63: 4952.99 | P63: 0 | Q63: =M63*O63-P63 -> 4952.99 | R63: 0.18 | S63: IGST | T63: =IF(S63="IGST",ROUND(Q63*R63,2),0) -> 891.54 | U63: =IF(S63="CGST+SGST",ROUND(Q63*R63/2,2),0) -> 0 | V63: =U63 -> 0 | W63: 0 | X63: =Q63+T63+U63+V63+W63 -> 5844.53 | Y63: =ROUND(Q63*AT63,0) -> 99 | Z63: =X63-Y63 -> 5745.53 | AD63: Chhattisgarh (22) | AE63: 06AAFCN6567R1ZL | AF63: Haryana (06) | AJ63: A/c FAR322055 | AK63: 829ad458c1fda3cd28fd33a9aa6a8edcff77323d414e5d8d9745cf34eabb36c9 | AR63: No RCM – invoice states RCM Applicable: N; IGST 18% charged. ITC eligible (check GSTR-2B). Interest 2% p.m. on delay. | AS63: Sec 393(1) – contract/service (old 194C), 2% (company). Confirm with CA. | AT63: 0.02
A64: 60 | B64: Blue Dart Express Limited\2026829R00006958 31.08.26.pdf | C64: 2026829R00006958 | D64: 46265 | E64: =YEAR(D64) -> 2026 | F64: =TEXT(D64,"mmm") -> Aug | G64: Blue Dart Express Limited | H64: 29AAACB0446L1ZO | J64: Courier – Domestic Priority – Aug-26 | K64: 996812 | M64: 1 | N64: LOT | O64: 277.1 | P64: 0 | Q64: =M64*O64-P64 -> 277.1 | R64: 0.18 | S64: IGST | T64: =IF(S64="IGST",ROUND(Q64*R64,2),0) -> 49.88 | U64: =IF(S64="CGST+SGST",ROUND(Q64*R64/2,2),0) -> 0 | V64: =U64 -> 0 | W64: 0 | X64: =Q64+T64+U64+V64+W64 -> 326.98 | Y64: =ROUND(Q64*AT64,0) -> 6 | Z64: =X64-Y64 -> 320.98 | AD64: Karnataka (29) | AE64: 06AAFCN6567R1ZL | AF64: Haryana (06) | AJ64: A/c FAR322055 | AK64: a712c60e7dd3dd50dfb0b09ceb22f9644430207fee39ef406855fdb16d44a3e1 | AR64: No RCM – invoice states RCM Applicable: N; IGST 18% charged. ITC eligible (check GSTR-2B). Interest 2% p.m. on delay. | AS64: Sec 393(1) – contract/service (old 194C), 2% (company). Confirm with CA. | AT64: 0.02
A65: 61 | B65: Blue Dart Express Limited\2026829R00006959 31.08.26.pdf | C65: 2026829R00006959 | D65: 46265 | E65: =YEAR(D65) -> 2026 | F65: =TEXT(D65,"mmm") -> Aug | G65: Blue Dart Express Limited | H65: 29AAACB0446L1ZO | J65: Courier – SFC Standard – Aug-26 | K65: 996812 | M65: 1 | N65: LOT | O65: 817.23 | P65: 0 | Q65: =M65*O65-P65 -> 817.23 | R65: 0.18 | S65: IGST | T65: =IF(S65="IGST",ROUND(Q65*R65,2),0) -> 147.1 | U65: =IF(S65="CGST+SGST",ROUND(Q65*R65/2,2),0) -> 0 | V65: =U65 -> 0 | W65: 0 | X65: =Q65+T65+U65+V65+W65 -> 964.33 | Y65: =ROUND(Q65*AT65,0) -> 16 | Z65: =X65-Y65 -> 948.33 | AD65: Karnataka (29) | AE65: 06AAFCN6567R1ZL | AF65: Haryana (06) | AJ65: A/c FAR322055 | AK65: 218b687fbde4463a8a5961939c8683c71a79bcdf59f3914f14ce66e54732db9e | AR65: No RCM – invoice states RCM Applicable: N; IGST 18% charged. ITC eligible (check GSTR-2B). Interest 2% p.m. on delay. | AS65: Sec 393(1) – contract/service (old 194C), 2% (company). Confirm with CA. | AT65: 0.02
A66: 62 | B66: Blue Dart Express Limited\2026806R00002352 31.08.26.pdf | C66: 2026806R00002352 | D66: 46265 | E66: =YEAR(D66) -> 2026 | F66: =TEXT(D66,"mmm") -> Aug | G66: Blue Dart Express Limited | H66: 06AAACB0446L1ZW | J66: Courier – SFC Standard – Aug-26 | K66: 996812 | M66: 1 | N66: LOT | O66: 3497.55 | P66: 0 | Q66: =M66*O66-P66 -> 3497.55 | R66: 0.18 | S66: CGST+SGST | T66: =IF(S66="IGST",ROUND(Q66*R66,2),0) -> 0 | U66: =IF(S66="CGST+SGST",ROUND(Q66*R66/2,2),0) -> 314.78 | V66: =U66 -> 314.78 | W66: 0 | X66: =Q66+T66+U66+V66+W66 -> 4127.11 | Y66: =ROUND(Q66*AT66,0) -> 70 | Z66: =X66-Y66 -> 4057.11 | AD66: Haryana (06) | AE66: 06AAFCN6567R1ZL | AF66: Haryana (06) | AJ66: A/c FAR322055 | AK66: f27896688b7a9b8aa04febab08a8729dcd9f6ab4b6d8dc8347f508cc61d8f47c | AR66: No RCM – invoice states RCM Applicable: N; CGST 9% + SGST 9% charged. ITC eligible (check GSTR-2B). Interest 2% p.m. on delay. | AS66: Sec 393(1) – contract/service (old 194C), 2% (company). Confirm with CA. | AT66: 0.02
A67: 63 | B67: DTDC Express Limited\CH0427TS002362 31.08.26.pdf | C67: CH0427TS002362 | D67: 46265 | E67: =YEAR(D67) -> 2026 | F67: =TEXT(D67,"mmm") -> Aug | G67: DTDC Express Limited | H67: 04AAACD8017H1Z0 | J67: Courier services Aug-2026 (freight 1720.00, fuel 206.40) | K67: 996812 | M67: 1 | N67: LOT | O67: 1926.4 | P67: 0 | Q67: =M67*O67-P67 -> 1926.4 | R67: 0.18 | S67: CGST+SGST | T67: =IF(S67="IGST",ROUND(Q67*R67,2),0) -> 0 | U67: =IF(S67="CGST+SGST",ROUND(Q67*R67/2,2),0) -> 173.38 | V67: =U67 -> 173.38 | W67: 0 | X67: =Q67+T67+U67+V67+W67 -> 2273.16 | Y67: =ROUND(Q67*AT67,0) -> 39 | Z67: =X67-Y67 -> 2234.16 | AD67: Chandigarh (04) | AE67: 04AAFCN6567R1ZP | AF67: Chandigarh (04) | AJ67: Client GL7838 | AK67: a5d8be5bc634f9ffc4b14ba3e3ccb1c9f5acf0130806a04c42fc24ab1fd1fe5b | AR67: No RCM – invoice states reverse charge NO; CGST 9% + UTGST 9% charged. ITC eligible (check GSTR-2B). Due 30-09-2026. | AS67: Sec 393(1) – contract/service (old 194C), 2% (company). Confirm with CA. | AT67: 0.02
... A86: 82 | B86: DLF Home Developers Limited\2220016358 08.07.26.pdf | C86: 2220016358 | D86: 46211 | E86: =YEAR(D86) -> 2026 | F86: =TEXT(D86,"mmm") -> Jul | G86: DLF Home Developers Limited | H86: 07AACCD0037H1Z4 | J86: Maintenance SH-51 DLF Mid Town Plaza 01.07.2026-31.07.2026 | K86: 995419 | M86: 1133 | N86: SQFT | O86: 32 | P86: 0 | Q86: =M86*O86-P86 -> 36256 | R86: 0.18 | S86: CGST+SGST | T86: =IF(S86="IGST",ROUND(Q86*R86,2),0) -> 0 | U86: =IF(S86="CGST+SGST",ROUND(Q86*R86/2,2),0) -> 3263.04 | V86: =U86 -> 3263.04 | W86: 0 | X86: =Q86+T86+U86+V86+W86 -> 42782.08 | Y86: =ROUND(Q86*AT86,0) -> 725 | Z86: =X86-Y86 -> 42057.08 | AD86: Delhi (07) | AE86: 07AAFCN6567R1ZJ | AF86: Delhi (07) | AJ86: Lease 1002300092 | AK86: c08b38f05669b0b1f6f1065422ad25954378e293e4d160ae60a87c5c0030d1df | AR86: No RCM – forward charge; CGST 9% + SGST 9% charged by supplier. ITC eligible (check GSTR-2B). | AS86: Sec 393(1) – contract/service (old 194C), 2% (company). Confirm with CA. | AT86: 0.02
A87: 83 | B87: DLF Home Developers Limited\2210014043 16.07.26.pdf | C87: 2210014043 | D87: 46219 | E87: =YEAR(D87) -> 2026 | F87: =TEXT(D87,"mmm") -> Jul | G87: DLF Home Developers Limited | H87: 07AACCD0037H1Z4 | J87: Rent – Revenue share 16% on general sales ₹3,82,826, 01.06.2026-30.06.2026 | K87: 997212 | M87: 1 | N87: LOT | O87: 61252 | P87: 0 | Q87: =M87*O87-P87 -> 61252 | R87: 0.18 | S87: CGST+SGST | T87: =IF(S87="IGST",ROUND(Q87*R87,2),0) -> 0 | U87: =IF(S87="CGST+SGST",ROUND(Q87*R87/2,2),0) -> 5512.68 | V87: =U87 -> 5512.68 | W87: 0 | X87: =Q87+T87+U87+V87+W87 -> 72277.36 | Y87: =ROUND(Q87*AT87,0) -> 6125 | Z87: =X87-Y87 -> 66152.36 | AD87: Delhi (07) | AE87: 07AAFCN6567R1ZJ | AF87: Delhi (07) | AJ87: Lease 1002300092 | AR87: No RCM – forward charge; CGST 9% + SGST 9% charged by supplier. ITC eligible (check GSTR-2B). | AS87: Sec 393(1) – rent of land/building (old 194-I), 10%. | AT87: 0.1
A88: 84 | B88: DLF Home Developers Limited\220060004861 17.07.26.pdf | C88: 220060004861 | D88: 46220 | E88: =YEAR(D88) -> 2026 | F88: =TEXT(D88,"mmm") -> Jul | G88: DLF Home Developers Limited | H88: 07AACCD0037H1Z4 | J88: EB up to June-26 – consumption 2,268 units @ ₹14.36 (meter 27160000) | M88: 2268 | N88: KWH | O88: 14.36 | P88: 0 | Q88: =M88*O88-P88 -> 32568.48 | R88: 0 | S88: Exempt (electricity) | T88: =IF(S88="IGST",ROUND(Q88*R88,2),0) -> 0 | U88: =IF(S88="CGST+SGST",ROUND(Q88*R88/2,2),0) -> 0 | V88: =U88 -> 0 | W88: 0 | X88: =Q88+T88+U88+V88+W88 -> 32568.48 | Y88: =ROUND(Q88*AT88,0) -> 0 | Z88: =X88-Y88 -> 32568.48 | AD88: Delhi (07) | AE88: 07AAFCN6567R1ZJ | AF88: Delhi (07) | AJ88: Lease 1002300092 | AR88: Electricity – exempt supply (Notif. 02/2017-CT(Rate) entry 104), no GST, no ITC. | AS88: Electricity charges – TDS generally not applicable; confirm with CA. | AT88: 0
A89: 85 | B89: DLF Home Developers Limited\2210016694 01.08.26.pdf | C89: 2210016694 | D89: 46235 | E89: =YEAR(D89) -> 2026 | F89: =TEXT(D89,"mmm") -> Aug | G89: DLF Home Developers Limited | H89: 07AACCD0037H1Z4 | J89: Rent (Retail) SH-51 DLF Mid Town Plaza 01.08.2026-31.08.2026 | K89: 997212 | M89: 1133 | N89: SQFT | O89: 400 | P89: 0 | Q89: =M89*O89-P89 -> 453200 | R89: 0.18 | S89: CGST+SGST | T89: =IF(S89="IGST",ROUND(Q89*R89,2),0) -> 0 | U89: =IF(S89="CGST+SGST",ROUND(Q89*R89/2,2),0) -> 40788 | V89: =U89 -> 40788 | W89: 0 | X89: =Q89+T89+U89+V89+W89 -> 534776 | Y89: =ROUND(Q89*AT89,0) -> 45320 | Z89: =X89-Y89 -> 489456 | AD89: Delhi (07) | AE89: 07AAFCN6567R1ZJ | AF89: Delhi (07) | AJ89: Lease 1002300092 | AK89: 7cf34c5472f559baaef7524a8f44c29a818cb4c479503bf9bf575cede6df50d3 | AR89: No RCM – forward charge; CGST 9% + SGST 9% charged by supplier. ITC eligible (check GSTR-2B). | AS89: Sec 393(1) – rent of land/building (old 194-I), 10%. | AT89: 0.1
A90: 86 | B90: DLF Home Developers Limited\2220020581 01.08.26.pdf | C90: 2220020581 | D90: 46235 | E90: =YEAR(D90) -> 2026 | F90: =TEXT(D90,"mmm") -> Aug | G90: DLF Home Developers Limited | H90: 07AACCD0037H1Z4 | J90: Maintenance SH-51 DLF Mid Town Plaza 01.08.2026-31.08.2026 | K90: 995419 | M90: 1133 | N90: SQFT | O90: 32 | P90: 0 | Q90: =M90*O90-P90 -> 36256 | R90: 0.18 | S90: CGST+SGST | T90: =IF(S90="IGST",ROUND(Q90*R90,2),0) -> 0 | U90: =IF(S90="CGST+SGST",ROUND(Q90*R90/2,2),0) -> 3263.04 | V90: =U90 -> 3263.04 | W90: 0 | X90: =Q90+T90+U90+V90+W90 -> 42782.08 | Y90: =ROUND(Q90*AT90,0) -> 725 | Z90: =X90-Y90 -> 42057.08 | AD90: Delhi (07) | AE90: 07AAFCN6567R1ZJ | AF90: Delhi (07) | AJ90: Lease 1002300092 | AK90: f26f869bacd5bf17fa030a9e1168e7685a559b91bb1e98f95d737b12a56442b7 | AR90: No RCM – forward charge; CGST 9% + SGST 9% charged by supplier. ITC eligible (check GSTR-2B). | AS90: Sec 393(1) – contract/service (old 194C), 2% (company). Confirm with CA. | AT90: 0.02
A91: 87 | B91: DLF Home Developers Limited\220060005850 05.08.26.pdf | C91: 220060005850 | D91: 46239 | E91: =YEAR(D91) -> 2026 | F91: =TEXT(D91,"mmm") -> Aug | G91: DLF Home Developers Limited | H91: 07AACCD0037H1Z4 | J91: EB up to July-26 – consumption 2,322 units @ ₹14.36 (meter 27160000) | M91: 2322 | N91: KWH | O91: 14.36 | P91: 0 | Q91: =M91*O91-P91 -> 33343.92 | R91: 0 | S91: Exempt (electricity) | T91: =IF(S91="IGST",ROUND(Q91*R91,2),0) -> 0 | U91: =IF(S91="CGST+SGST",ROUND(Q91*R91/2,2),0) -> 0 | V91: =U91 -> 0 | W91: 0 | X91: =Q91+T91+U91+V91+W91 -> 33343.92 | Y91: =ROUND(Q91*AT91,0) -> 0 | Z91: =X91-Y91 -> 33343.92 | AD91: Delhi (07) | AE91: 07AAFCN6567R1ZJ | AF91: Delhi (07) | AJ91: Lease 1002300092 | AR91: Electricity – exempt supply (Notif. 02/2017-CT(Rate) entry 104), no GST, no ITC. | AS91: Electricity charges – TDS generally not applicable; confirm with CA. | AT91: 0
A92: 88 | B92: DLF Home Developers Limited\220060006482 21.08.26.pdf | C92: 220060006482 | D92: 46255 | E92: =YEAR(D92) -> 2026 | F92: =TEXT(D92,"mmm") -> Aug | G92: DLF Home Developers Limited | H92: 07AACCD0037H1Z4 | J92: EB – Additional load 14.07 kW @ ₹10,000 | K92: 995419 | M92: 14.07 | N92: KW | O92: 10000 | P92: 0 | Q92: =M92*O92-P92 -> 140700 | R92: 0.18 | S92: CGST+SGST | T92: =IF(S92="IGST",ROUND(Q92*R92,2),0) -> 0 | U92: =IF(S92="CGST+SGST",ROUND(Q92*R92/2,2),0) -> 12663 | V92: =U92 -> 12663 | W92: 0 | X92: =Q92+T92+U92+V92+W92 -> 166026 | Y92: =ROUND(Q92*AT92,0) -> 2814 | Z92: =X92-Y92 -> 163212 | AD92: Delhi (07) | AE92: 07AAFCN6567R1ZJ | AF92: Delhi (07) | AJ92: Lease 1002300092 | AK92: 33b22f2def0bdf8d2ef1e7f22c45c694a1b9e5686ee32ba7ccff7088c9c39477 | AR92: No RCM – forward charge; CGST 9% + SGST 9% charged by supplier. ITC eligible (check GSTR-2B). | AS92: Sec 393(1) – contract/service (old 194C), 2% (company). Confirm with CA. | AT92: 0.02
A93: 89 | B93: DLF Home Developers Limited\220040012052 23.09.26.pdf | C93: 220040012052 | D93: 46288 | E93: =YEAR(D93) -> 2026 | F93: =TEXT(D93,"mmm") -> Sep | G93: DLF Home Developers Limited | H93: 07AACCD0037H1Z4 | J93: Electrical energy SH-51 01.08.2026-31.08.2026 – 2,132 units @ ₹14.36 (meter 27160000, reading 11053→13185) | M93: 2132 | N93: KWH | O93: 14.36 | P93: 0 | Q93: =M93*O93-P93 -> 30615.52 | R93: 0 | S93: Exempt (electricity) | T93: =IF(S93="IGST",ROUND(Q93*R93,2),0) -> 0 | U93: =IF(S93="CGST+SGST",ROUND(Q93*R93/2,2),0) -> 0 | V93: =U93 -> 0 | W93: 0 | X93: =Q93+T93+U93+V93+W93 -> 30615.52 | Y93: =ROUND(Q93*AT93,0) -> 0 | Z93: =X93-Y93 -> 30615.52 | AD93: Delhi (07) | AE93: 07AAFCN6567R1ZJ | AF93: Delhi (07) | AJ93: Lease 1002300092 | AR93: Electricity – exempt supply (Notif. 02/2017-CT(Rate) entry 104), no GST, no ITC. | AS93: Electricity charges – TDS generally not applicable; confirm with CA. | AT93: 0
A94: 90 | B94: DLF Home Developers Limited\220060010971 24.09.26.pdf | C94: 220060010971 | D94: 46289 | E94: =YEAR(D94) -> 2026 | F94: =TEXT(D94,"mmm") -> Sep | G94: DLF Home Developers Limited | H94: 07AACCD0037H1Z4 | J94: Revenue share Jul-26: 1-12 Jul ₹1,37,820 @16% & 13-31 Jul ₹6,94,066 @16% (net of earlier billing) | K94: 997212 | M94: 1 | N94: LOT | O94: 22051.2 | P94: 0 | Q94: =M94*O94-P94 -> 22051.2 | R94: 0.18 | S94: CGST+SGST | T94: =IF(S94="IGST",ROUND(Q94*R94,2),0) -> 0 | U94: =IF(S94="CGST+SGST",ROUND(Q94*R94/2,2),0) -> 1984.61 | V94: =U94 -> 1984.61 | W94: 0 | X94: =Q94+T94+U94+V94+W94 -> 26020.42 | Y94: =ROUND(Q94*AT94,0) -> 2205 | Z94: =X94-Y94 -> 23815.42 | AD94: Delhi (07) | AE94: 07AAFCN6567R1ZJ | AF94: Delhi (07) | AJ94: Lease 1002300092 | AK94: aa67f64cecc58ad15fd4318454a81de1c5dab41f9d9fa438ef3884c4392ed13f | AR94: No RCM – forward charge; CGST 9% + SGST 9% charged by supplier. ITC eligible (check GSTR-2B). | AS94: Sec 393(1) – rent of land/building (old 194-I), 10%. | AT94: 0.1
A95: 91 | B95: Surbhi Sethi\013-2026-27 17.09.26.pdf | C95: 013/2026-27 | D95: 46282 | E95: =YEAR(D95) -> 2026 | F95: =TEXT(D95,"mmm") -> Sep | G95: Surbhi Sethi | H95: 07CGFPS5289G1ZV | J95: Influencer Marketing Activity for Nicobar | K95: 998365 | M95: 1 | N95: NOS | O95: 30000 | P95: 0 | Q95: =M95*O95-P95 -> 30000 | R95: 0.18 | S95: CGST+SGST | T95: =IF(S95="IGST",ROUND(Q95*R95,2),0) -> 0 | U95: =IF(S95="CGST+SGST",ROUND(Q95*R95/2,2),0) -> 2700 | V95: =U95 -> 2700 | W95: 0 | X95: =Q95+T95+U95+V95+W95 -> 35400 | Y95: =ROUND(Q95*AT95,0) -> 0 | Z95: =X95-Y95 -> 35400 | AD95: Delhi (07) | AE95: 07AAFCN6567R1ZJ | AF95: Delhi (07) | AR95: No RCM – forward charge; CGST 9% + SGST 9% charged by supplier. ITC eligible (check GSTR-2B). | AS95: Sec 393(1) – professional/advertising fees (old 194J), 10%. Nil now: ₹30,000 below ₹50,000 FY threshold; deduct if FY total exceeds it. | AT95: 0
A96: 92 | B96: Simran\1 24.09.26.pdf | C96: 1 | D96: 46289 | E96: =YEAR(D96) -> 2026 | F96: =TEXT(D96,"mmm") -> Sep | G96: Simran | J96: Modelling for fittings | M96: 1 | N96: NOS | O96: 8000 | P96: 0 | Q96: =M96*O96-P96 -> 8000 | R96: 0 | S96: No GST (unregistered) | T96: =IF(S96="IGST",ROUND(Q96*R96,2),0) -> 0 | U96: =IF(S96="CGST+SGST",ROUND(Q96*R96/2,2),0) -> 0 | V96: =U96 -> 0 | W96: 0 | X96: =Q96+T96+U96+V96+W96 -> 8000 | Y96: =ROUND(Q96*AT96,0) -> 0 | Z96: =X96-Y96 -> 8000 | AD96: Delhi | AF96: Delhi (07) | AJ96: PAN QWZPS5661C | AR96: No RCM – unregistered individual; modelling service not notified under Sec 9(3)/9(4). No GST, no ITC. | AS96: Sec 393(1) – professional fees (old 194J), 10%. Nil now: ₹8,000 below ₹50,000 FY threshold. (Or 194C – confirm with CA.) | AT96: 0
A97: 93 | B97: V Dine Unit of VRSM Enterprises LLP\VDINEAUG02 01.08.26.pdf | C97: VDINEAUG02 | D97: 46235 | E97: =YEAR(D97) -> 2026 | F97: =TEXT(D97,"mmm") -> Aug | G97: V Dine Unit of VRSM Enterprises LLP | H97: 30AAOFV6519M2ZO | J97: Rent – store at Assagao, Goa (GAN) for Aug-2026 | M97: 1 | N97: LOT | O97: 250000 | P97: 0 | Q97: =M97*O97-P97 -> 250000 | R97: 0.18 | S97: CGST+SGST | T97: =IF(S97="IGST",ROUND(Q97*R97,2),0) -> 0 | U97: =IF(S97="CGST+SGST",ROUND(Q97*R97/2,2),0) -> 22500 | V97: =U97 -> 22500 | W97: 0 | X97: =Q97+T97+U97+V97+W97 -> 295000 | Y97: =ROUND(Q97*AT97,0) -> 25000 | Z97: =X97-Y97 -> 270000 | AA97: GAN | AB97: NBV03991 | AC97: 4038001 | AD97: Goa (30) | AE97: 07AAFCN6567R1ZJ | AF97: Goa (30) | AJ97: Nicobar PI26GAN0000065 (vendor NBV03991) | AR97: No RCM – CGST 9% + SGST 9% shown. NOTE: source is Nicobar's internal Purchase Invoice voucher, not the supplier's tax invoice – obtain the original invoice for ITC. | AS97: Sec 393(1) – rent of land/building (old 194-I), 10%. | AT97: 0.1
A98: 94 | B98: Clay Craft India Limited\MN-10087-26-27 26.09.26.pdf | C98: MN/10087/26-27 | D98: 46291 | E98: =YEAR(D98) -> 2026 | F98: =TEXT(D98,"mmm") -> Sep | G98: Clay Craft India Limited | H98: 08AAACC6866D1ZO | I98: FG004716 | J98: NB Botanical Coasters 12 Set of 4 Pcs (NBI034275) | K98: 69120090 | L98: 18 | M98: 216 | N98: SET | O98: 283 | P98: 0 | Q98: =M98*O98-P98 -> 61128 | R98: 0.05 | S98: IGST | T98: =IF(S98="IGST",ROUND(Q98*R98,2),0) -> 3056.4 | U98: =IF(S98="CGST+SGST",ROUND(Q98*R98/2,2),0) -> 0 | V98: =U98 -> 0 | W98: 0 | X98: =Q98+T98+U98+V98+W98 -> 64184.4 | Y98: =ROUND(Q98*AT98,0) -> 61 | Z98: =X98-Y98 -> 64123.4 | AD98: Rajasthan (08) | AE98: 06AAFCN6567R1ZL | AF98: Haryana (06) | AG98: 26000000539 | AH98: 46211 | AI98: 10087 | AJ98: 10037 | AO98: Shyam Cargo Movers | AP98: 21099 | AQ98: MH43CK2130 | AR98: No RCM – forward charge; goods, IGST 5% charged by supplier. ITC eligible (check GSTR-2B). IRN/Ack/E-way bill not printed on the PDF. Terms Net-30; interest @18% after 45 days. | AS98: Sec 393(1) – purchase of goods (old 194Q), code 1031. Apply only if FY purchases from this supplier > ₹50 L (on excess). | AT98: 0.001
A99: 95 | B99: Clay Craft India Limited\MN-10087-26-27 26.09.26.pdf | C99: MN/10087/26-27 | D99: 46291 | E99: =YEAR(D99) -> 2026 | F99: =TEXT(D99,"mmm") -> Sep | G99: Clay Craft India Limited | H99: 08AAACC6866D1ZO | I99: FG004802 | J99: NB Tribe Coasters 12 Set of 4 Pcs (NBI034276) | K99: 69120090 | L99: 8 | M99: 96 | N99: SET | O99: 283 | P99: 0 | Q99: =M99*O99-P99 -> 27168 | R99: 0.05 | S99: IGST | T99: =IF(S99="IGST",ROUND(Q99*R99,2),0) -> 1358.4 | U99: =IF(S99="CGST+SGST",ROUND(Q99*R99/2,2),0) -> 0 | V99: =U99 -> 0 | W99: 0.2 | X99: =Q99+T99+U99+V99+W99 -> 28526.6 | Y99: =ROUND(Q99*AT99,0) -> 27 | Z99: =X99-Y99 -> 28499.6 | AD99: Rajasthan (08) | AE99: 06AAFCN6567R1ZL | AF99: Haryana (06) | AG99: 26000000539 | AH99: 46211 | AI99: 10087 | AJ99: 10037 | AO99: Shyam Cargo Movers | AP99: 21099 | AQ99: MH43CK2130 | AR99: No RCM – forward charge; goods, IGST 5% charged by supplier. ITC eligible (check GSTR-2B). IRN/Ack/E-way bill not printed on the PDF. Terms Net-30; interest @18% after 45 days. | AS99: Sec 393(1) – purchase of goods (old 194Q), code 1031. Apply only if FY purchases from this supplier > ₹50 L (on excess). | AT99: 0.001
A100: 96 | B100: Prezotech Solutions Pvt Ltd\INV-26-27-0901 30.06.26.pdf | C100: INV/26-27/0901 | D100: 46203 | E100: =YEAR(D100) -> 2026 | F100: =TEXT(D100,"mmm") -> Jun | G100: Prezotech Solutions Pvt Ltd | H100: 07AAICP6830G1ZB | J100: Prezotech Label 100x150mm CR (300/Labels) – sticker labels, single colour printed (Sticker Fragile Glass) | K100: 48219010 | M100: 30000 | N100: PCS | O100: 0.84 | P100: 0 | Q100: =M100*O100-P100 -> 25200 | R100: 0.18 | S100: IGST | T100: =IF(S100="IGST",ROUND(Q100*R100,2),0) -> 4536 | U100: =IF(S100="CGST+SGST",ROUND(Q100*R100/2,2),0) -> 0 | V100: =U100 -> 0 | W100: 0 | X100: =Q100+T100+U100+V100+W100 -> 29736 | Y100: =ROUND(Q100*AT100,0) -> 0 | Z100: =X100-Y100 -> 29736 | AD100: Delhi (07) | AE100: 06AAFCN6567R1ZL | AF100: Haryana (06) | AG100: PO26000000590 | AK100: e6e026e23692210b38f9474a45de03e7f3b6de174a0833831a502c0a2d3cd7f2 | AL100: 172620584106073 | AM100: 2026-06-30 18:07 | AR100: No RCM – forward charge; goods, IGST 18% charged by supplier. ITC eligible (check GSTR-2B). Terms Net 30 – due 30-07-2026 (overdue; 2% p.m. charged beyond terms). ₹1,500 block charge is one-time (first order). | AS100: Sec 393(1) – purchase of goods (old 194Q). Apply only if FY purchases from this supplier > ₹50 L – nil assumed. | AT100: 0
A101: 97 | B101: Prezotech Solutions Pvt Ltd\INV-26-27-0901 30.06.26.pdf | C101: INV/26-27/0901 | D101: 46203 | E101: =YEAR(D101) -> 2026 | F101: =TEXT(D101,"mmm") -> Jun | G101: Prezotech Solutions Pvt Ltd | H101: 07AAICP6830G1ZB | J101: Block charge – one-time charges | K101: 84425090 | M101: 1 | N101: UNIT | O101: 1500 | P101: 0 | Q101: =M101*O101-P101 -> 1500 | R101: 0.18 | S101: IGST | T101: =IF(S101="IGST",ROUND(Q101*R101,2),0) -> 270 | U101: =IF(S101="CGST+SGST",ROUND(Q101*R101/2,2),0) -> 0 | V101: =U101 -> 0 | W101: 0 | X101: =Q101+T101+U101+V101+W101 -> 1770 | Y101: =ROUND(Q101*AT101,0) -> 0 | Z101: =X101-Y101 -> 1770 | AD101: Delhi (07) | AE101: 06AAFCN6567R1ZL | AF101: Haryana (06) | AG101: PO26000000590 | AK101: e6e026e23692210b38f9474a45de03e7f3b6de174a0833831a502c0a2d3cd7f2 | AL101: 172620584106073 | AM101: 2026-06-30 18:07 | AR101: No RCM – forward charge; goods, IGST 18% charged by supplier. ITC eligible (check GSTR-2B). Terms Net 30 – due 30-07-2026 (overdue; 2% p.m. charged beyond terms). ₹1,500 block charge is one-time (first order). | AS101: Sec 393(1) – purchase of goods (old 194Q). Apply only if FY purchases from this supplier > ₹50 L – nil assumed. | AT101: 0
A102: 98 | B102: Gowri Parvathy\010 30.09.26.pdf | C102: 010 | D102: 46295 | E102: =YEAR(D102) -> 2026 | F102: =TEXT(D102,"mmm") -> Sep | G102: Gowri Parvathy | J102: 1 collab reel + 2 months ad rights (Sept store ad) | M102: 1 | N102: NOS | O102: 50000 | P102: 0 | Q102: =M102*O102-P102 -> 50000 | R102: 0 | S102: No GST (unregistered) | T102: =IF(S102="IGST",ROUND(Q102*R102,2),0) -> 0 | U102: =IF(S102="CGST+SGST",ROUND(Q102*R102/2,2),0) -> 0 | V102: =U102 -> 0 | W102: 0 | X102: =Q102+T102+U102+V102+W102 -> 50000 | Y102: =ROUND(Q102*AT102,0) -> 0 | Z102: =X102-Y102 -> 50000 | AD102: Karnataka (29) | AE102: 07AAFCN6567R1ZJ | AF102: Delhi (07) | AJ102: PAN GYNPP1895M | AR102: No RCM – unregistered individual; influencer/advertising service not notified under Sec 9(3)/9(4). No GST, no ITC. PDF also contains PAN card and cancelled cheque (Federal Bank). | AS102: Sec 393(1) – professional/advertising fees (old 194J), 10%. Nil now: ₹50,000 does not exceed the ₹50,000 FY threshold; deduct 10% if FY total exceeds it. | AT102: 0
A103: 99 | B103: A & S Creations\065-2026-2027 26.09.26.pdf | C103: 065/2026-2027 | D103: 46291 | E103: =YEAR(D103) -> 2026 | F103: =TEXT(D103,"mmm") -> Sep | G103: A & S Creations | H103: 07ABNFA6509L1Z2 | J103: Grazing Experience by Paris my Love – 25 pax (cheese, dips, breads, fruits, olives & nuts) – 50% discount | M103: 1 | N103: LOT | O103: 25000 | P103: 12500 | Q103: =M103*O103-P103 -> 12500 | R103: 0.05 | S103: CGST+SGST | T103: =IF(S103="IGST",ROUND(Q103*R103,2),0) -> 0 | U103: =IF(S103="CGST+SGST",ROUND(Q103*R103/2,2),0) -> 312.5 | V103: =U103 -> 312.5 | W103: 0 | X103: =Q103+T103+U103+V103+W103 -> 13125 | Y103: =ROUND(Q103*AT103,0) -> 0 | Z103: =X103-Y103 -> 13125 | AD103: Delhi (07) | AE103: 07AAFCN6567R2ZI | AF103: Delhi (07) | AJ103: GK2 store event 26-09-2026 – grazing table | AR103: No RCM – GST @5% shown as one line; split here as CGST 2.5% + SGST 2.5% (intra-Delhi). Outdoor catering at 5% – ITC not available. Document titled "Invoice" (not "Tax Invoice"), no HSN/SAC, and buyer GSTIN printed as 07AAFCN6567R2ZI (Nicobar Delhi GSTIN is 07AAFCN6567R1ZJ) – ask supplier for a corrected tax invoice. 100% advance terms. | AS103: Sec 393(1) – contract/catering (old 194C), 2% (firm). Nil now: ₹24,988 below ₹30,000 single-bill / ₹1 L FY threshold. | AT103: 0
A104: 100 | B104: A & S Creations\065-2026-2027 26.09.26.pdf | C104: 065/2026-2027 | D104: 46291 | E104: =YEAR(D104) -> 2026 | F104: =TEXT(D104,"mmm") -> Sep | G104: A & S Creations | H104: 07ABNFA6509L1Z2 | J104: Black olive tapenade – 50% discount | M104: 20 | N104: PORTION | O104: 150 | P104: 1500 | Q104: =M104*O104-P104 -> 1500 | R104: 0.05 | S104: CGST+SGST | T104: =IF(S104="IGST",ROUND(Q104*R104,2),0) -> 0 | U104: =IF(S104="CGST+SGST",ROUND(Q104*R104/2,2),0) -> 37.5 | V104: =U104 -> 37.5 | W104: 0 | X104: =Q104+T104+U104+V104+W104 -> 1575 | Y104: =ROUND(Q104*AT104,0) -> 0 | Z104: =X104-Y104 -> 1575 | AD104: Delhi (07) | AE104: 07AAFCN6567R2ZI | AF104: Delhi (07) | AJ104: GK2 store event 26-09-2026 – grazing table | AR104: No RCM – GST @5% shown as one line; split here as CGST 2.5% + SGST 2.5% (intra-Delhi). Outdoor catering at 5% – ITC not available. Document titled "Invoice" (not "Tax Invoice"), no HSN/SAC, and buyer GSTIN printed as 07AAFCN6567R2ZI (Nicobar Delhi GSTIN is 07AAFCN6567R1ZJ) – ask supplier for a corrected tax invoice. 100% advance terms. | AS104: Sec 393(1) – contract/catering (old 194C), 2% (firm). Nil now: ₹24,988 below ₹30,000 single-bill / ₹1 L FY threshold. | AT104: 0
A105: 101 | B105: A & S Creations\065-2026-2027 26.09.26.pdf | C105: 065/2026-2027 | D105: 46291 | E105: =YEAR(D105) -> 2026 | F105: =TEXT(D105,"mmm") -> Sep | G105: A & S Creations | H105: 07ABNFA6509L1Z2 | J105: Mushroom vol au vents – 50% discount | M105: 20 | N105: PORTION | O105: 150 | P105: 1500 | Q105: =M105*O105-P105 -> 1500 | R105: 0.05 | S105: CGST+SGST | T105: =IF(S105="IGST",ROUND(Q105*R105,2),0) -> 0 | U105: =IF(S105="CGST+SGST",ROUND(Q105*R105/2,2),0) -> 37.5 | V105: =U105 -> 37.5 | W105: 0 | X105: =Q105+T105+U105+V105+W105 -> 1575 | Y105: =ROUND(Q105*AT105,0) -> 0 | Z105: =X105-Y105 -> 1575 | AD105: Delhi (07) | AE105: 07AAFCN6567R2ZI | AF105: Delhi (07) | AJ105: GK2 store event 26-09-2026 – grazing table | AR105: No RCM – GST @5% shown as one line; split here as CGST 2.5% + SGST 2.5% (intra-Delhi). Outdoor catering at 5% – ITC not available. Document titled "Invoice" (not "Tax Invoice"), no HSN/SAC, and buyer GSTIN printed as 07AAFCN6567R2ZI (Nicobar Delhi GSTIN is 07AAFCN6567R1ZJ) – ask supplier for a corrected tax invoice. 100% advance terms. | AS105: Sec 393(1) – contract/catering (old 194C), 2% (firm). Nil now: ₹24,988 below ₹30,000 single-bill / ₹1 L FY threshold. | AT105: 0
A106: 102 | B106: A & S Creations\065-2026-2027 26.09.26.pdf | C106: 065/2026-2027 | D106: 46291 | E106: =YEAR(D106) -> 2026 | F106: =TEXT(D106,"mmm") -> Sep | G106: A & S Creations | H106: 07ABNFA6509L1Z2 | J106: Phyllo cups with tomato, basil topped with cream cheese – 50% discount | M106: 20 | N106: PORTION | O106: 150 | P106: 1500 | Q106: =M106*O106-P106 -> 1500 | R106: 0.05 | S106: CGST+SGST | T106: =IF(S106="IGST",ROUND(Q106*R106,2),0) -> 0 | U106: =IF(S106="CGST+SGST",ROUND(Q106*R106/2,2),0) -> 37.5 | V106: =U106 -> 37.5 | W106: 0 | X106: =Q106+T106+U106+V106+W106 -> 1575 | Y106: =ROUND(Q106*AT106,0) -> 0 | Z106: =X106-Y106 -> 1575 | AD106: Delhi (07) | AE106: 07AAFCN6567R2ZI | AF106: Delhi (07) | AJ106: GK2 store event 26-09-2026 – grazing table | AR106: No RCM – GST @5% shown as one line; split here as CGST 2.5% + SGST 2.5% (intra-Delhi). Outdoor catering at 5% – ITC not available. Document titled "Invoice" (not "Tax Invoice"), no HSN/SAC, and buyer GSTIN printed as 07AAFCN6567R2ZI (Nicobar Delhi GSTIN is 07AAFCN6567R1ZJ) – ask supplier for a corrected tax invoice. 100% advance terms. | AS106: Sec 393(1) – contract/catering (old 194C), 2% (firm). Nil now: ₹24,988 below ₹30,000 single-bill / ₹1 L FY threshold. | AT106: 0
A107: 103 | B107: A & S Creations\065-2026-2027 26.09.26.pdf | C107: 065/2026-2027 | D107: 46291 | E107: =YEAR(D107) -> 2026 | F107: =TEXT(D107,"mmm") -> Sep | G107: A & S Creations | H107: 07ABNFA6509L1Z2 | J107: Chicken quiche – 50% discount | M107: 20 | N107: PORTION | O107: 175 | P107: 1750 | Q107: =M107*O107-P107 -> 1750 | R107: 0.05 | S107: CGST+SGST | T107: =IF(S107="IGST",ROUND(Q107*R107,2),0) -> 0 | U107: =IF(S107="CGST+SGST",ROUND(Q107*R107/2,2),0) -> 43.75 | V107: =U107 -> 43.75 | W107: 0 | X107: =Q107+T107+U107+V107+W107 -> 1837.5 | Y107: =ROUND(Q107*AT107,0) -> 0 | Z107: =X107-Y107 -> 1837.5 | AD107: Delhi (07) | AE107: 07AAFCN6567R2ZI | AF107: Delhi (07) | AJ107: GK2 store event 26-09-2026 – grazing table | AR107: No RCM – GST @5% shown as one line; split here as CGST 2.5% + SGST 2.5% (intra-Delhi). Outdoor catering at 5% – ITC not available. Document titled "Invoice" (not "Tax Invoice"), no HSN/SAC, and buyer GSTIN printed as 07AAFCN6567R2ZI (Nicobar Delhi GSTIN is 07AAFCN6567R1ZJ) – ask supplier for a corrected tax invoice. 100% advance terms. | AS107: Sec 393(1) – contract/catering (old 194C), 2% (firm). Nil now: ₹24,988 below ₹30,000 single-bill / ₹1 L FY threshold. | AT107: 0
A108: 104 | B108: A & S Creations\065-2026-2027 26.09.26.pdf | C108: 065/2026-2027 | D108: 46291 | E108: =YEAR(D108) -> 2026 | F108: =TEXT(D108,"mmm") -> Sep | G108: A & S Creations | H108: 07ABNFA6509L1Z2 | J108: Smoked salmon canape – 50% discount | M108: 20 | N108: PORTION | O108: 200 | P108: 2000 | Q108: =M108*O108-P108 -> 2000 | R108: 0.05 | S108: CGST+SGST | T108: =IF(S108="IGST",ROUND(Q108*R108,2),0) -> 0 | U108: =IF(S108="CGST+SGST",ROUND(Q108*R108/2,2),0) -> 50 | V108: =U108 -> 50 | W108: 0 | X108: =Q108+T108+U108+V108+W108 -> 2100 | Y108: =ROUND(Q108*AT108,0) -> 0 | Z108: =X108-Y108 -> 2100 | AD108: Delhi (07) | AE108: 07AAFCN6567R2ZI | AF108: Delhi (07) | AJ108: GK2 store event 26-09-2026 – grazing table | AR108: No RCM – GST @5% shown as one line; split here as CGST 2.5% + SGST 2.5% (intra-Delhi). Outdoor catering at 5% – ITC not available. Document titled "Invoice" (not "Tax Invoice"), no HSN/SAC, and buyer GSTIN printed as 07AAFCN6567R2ZI (Nicobar Delhi GSTIN is 07AAFCN6567R1ZJ) – ask supplier for a corrected tax invoice. 100% advance terms. | AS108: Sec 393(1) – contract/catering (old 194C), 2% (firm). Nil now: ₹24,988 below ₹30,000 single-bill / ₹1 L FY threshold. | AT108: 0
A109: 105 | B109: A & S Creations\065-2026-2027 26.09.26.pdf | C109: 065/2026-2027 | D109: 46291 | E109: =YEAR(D109) -> 2026 | F109: =TEXT(D109,"mmm") -> Sep | G109: A & S Creations | H109: 07ABNFA6509L1Z2 | J109: Macarons – 50% discount | M109: 15 | N109: PORTION | O109: 175 | P109: 1312.5 | Q109: =M109*O109-P109 -> 1312.5 | R109: 0.05 | S109: CGST+SGST | T109: =IF(S109="IGST",ROUND(Q109*R109,2),0) -> 0 | U109: =IF(S109="CGST+SGST",ROUND(Q109*R109/2,2),0) -> 32.81 | V109: =U109 -> 32.81 | W109: 0 | X109: =Q109+T109+U109+V109+W109 -> 1378.12 | Y109: =ROUND(Q109*AT109,0) -> 0 | Z109: =X109-Y109 -> 1378.12 | AD109: Delhi (07) | AE109: 07AAFCN6567R2ZI | AF109: Delhi (07) | AJ109: GK2 store event 26-09-2026 – grazing table | AR109: No RCM – GST @5% shown as one line; split here as CGST 2.5% + SGST 2.5% (intra-Delhi). Outdoor catering at 5% – ITC not available. Document titled "Invoice" (not "Tax Invoice"), no HSN/SAC, and buyer GSTIN printed as 07AAFCN6567R2ZI (Nicobar Delhi GSTIN is 07AAFCN6567R1ZJ) – ask supplier for a corrected tax invoice. 100% advance terms. | AS109: Sec 393(1) – contract/catering (old 194C), 2% (firm). Nil now: ₹24,988 below ₹30,000 single-bill / ₹1 L FY threshold. | AT109: 0
A110: 106 | B110: A & S Creations\065-2026-2027 26.09.26.pdf | C110: 065/2026-2027 | D110: 46291 | E110: =YEAR(D110) -> 2026 | F110: =TEXT(D110,"mmm") -> Sep | G110: A & S Creations | H110: 07ABNFA6509L1Z2 | J110: Eclairs (vanilla, pistachio, coffee) – 50% discount | M110: 15 | N110: PORTION | O110: 195 | P110: 1462.5 | Q110: =M110*O110-P110 -> 1462.5 | R110: 0.05 | S110: CGST+SGST | T110: =IF(S110="IGST",ROUND(Q110*R110,2),0) -> 0 | U110: =IF(S110="CGST+SGST",ROUND(Q110*R110/2,2),0) -> 36.56 | V110: =U110 -> 36.56 | W110: 0 | X110: =Q110+T110+U110+V110+W110 -> 1535.62 | Y110: =ROUND(Q110*AT110,0) -> 0 | Z110: =X110-Y110 -> 1535.62 | AD110: Delhi (07) | AE110: 07AAFCN6567R2ZI | AF110: Delhi (07) | AJ110: GK2 store event 26-09-2026 – grazing table | AR110: No RCM – GST @5% shown as one line; split here as CGST 2.5% + SGST 2.5% (intra-Delhi). Outdoor catering at 5% – ITC not available. Document titled "Invoice" (not "Tax Invoice"), no HSN/SAC, and buyer GSTIN printed as 07AAFCN6567R2ZI (Nicobar Delhi GSTIN is 07AAFCN6567R1ZJ) – ask supplier for a corrected tax invoice. 100% advance terms. | AS110: Sec 393(1) – contract/catering (old 194C), 2% (firm). Nil now: ₹24,988 below ₹30,000 single-bill / ₹1 L FY threshold. | AT110: 0
A111: 107 | B111: A & S Creations\065-2026-2027 26.09.26.pdf | C111: 065/2026-2027 | D111: 46291 | E111: =YEAR(D111) -> 2026 | F111: =TEXT(D111,"mmm") -> Sep | G111: A & S Creations | H111: 07ABNFA6509L1Z2 | J111: Tarts (lemon + chocolate) – 50% discount | M111: 15 | N111: PORTION | O111: 195 | P111: 1462.5 | Q111: =M111*O111-P111 -> 1462.5 | R111: 0.05 | S111: CGST+SGST | T111: =IF(S111="IGST",ROUND(Q111*R111,2),0) -> 0 | U111: =IF(S111="CGST+SGST",ROUND(Q111*R111/2,2),0) -> 36.56 | V111: =U111 -> 36.56 | W111: 0.14 | X111: =Q111+T111+U111+V111+W111 -> 1535.76 | Y111: =ROUND(Q111*AT111,0) -> 0 | Z111: =X111-Y111 -> 1535.76 | AD111: Delhi (07) | AE111: 07AAFCN6567R2ZI | AF111: Delhi (07) | AJ111: GK2 store event 26-09-2026 – grazing table | AR111: No RCM – GST @5% shown as one line; split here as CGST 2.5% + SGST 2.5% (intra-Delhi). Outdoor catering at 5% – ITC not available. Document titled "Invoice" (not "Tax Invoice"), no HSN/SAC, and buyer GSTIN printed as 07AAFCN6567R2ZI (Nicobar Delhi GSTIN is 07AAFCN6567R1ZJ) – ask supplier for a corrected tax invoice. 100% advance terms. | AS111: Sec 393(1) – contract/catering (old 194C), 2% (firm). Nil now: ₹24,988 below ₹30,000 single-bill / ₹1 L FY threshold. | AT111: 0
A112: 108 | B112: Cushman & Wakefield India Private Limited\MH-2026-09-2376 24.09.26.pdf | C112: MH-2026-09-2376 | D112: 46289 | E112: =YEAR(D112) -> 2026 | F112: =TEXT(D112,"mmm") -> Sep | G112: Cushman & Wakefield India Private Limited | H112: 27AAACC5006B1ZE | J112: Brokerage fee for sourcing lease space – Balvir Bungalow, Juhu Church Road, Juhu, Mumbai-400049 (1 month rent) | K112: 997222 | M112: 1 | N112: LOT | O112: 1325000 | P112: 0 | Q112: =M112*O112-P112 -> 1325000 | R112: 0.18 | S112: CGST+SGST | T112: =IF(S112="IGST",ROUND(Q112*R112,2),0) -> 0 | U112: =IF(S112="CGST+SGST",ROUND(Q112*R112/2,2),0) -> 119250 | V112: =U112 -> 119250 | W112: 0 | X112: =Q112+T112+U112+V112+W112 -> 1563500 | Y112: =ROUND(Q112*AT112,0) -> 26500 | Z112: =X112-Y112 -> 1537000 | AD112: Maharashtra (27) | AE112: 27AAFCN6567R1ZH | AF112: Maharashtra (27) | AJ112: APIPL_CUS_INV-2026-09-000008616 | AK112: a226be61f0033a3c65cb523b465c1b1d711d7218bd89cefaa62650d7e516747b | AR112: No RCM – forward charge; CGST 9% + SGST 9% (Maharashtra). ITC eligible against 27AAFCN6567R1ZH (check GSTR-2B). Revised invoice (bill-to Juhu store) received 01-10-2026; earlier copy with Lower Parel address has the same no. & IRN – not added. Net 30; 18% p.a. interest after. Nicobar email: realisation only once Juhu store goes live. | AS112: Sec 393(1) – commission/brokerage (old 194H), 2%. Confirm with CA. | AT112: 0.02
A113: 109 | B113: Niva's Designs\ND-26-27-043A 29.08.26.pdf | C113: ND/26-27/043A | D113: 46263 | E113: =YEAR(D113) -> 2026 | F113: =TEXT(D113,"mmm") -> Aug | G113: Niva's Designs | H113: 06BCAPS9611Q1Z0 | J113: Fabric – Cotton Slub with Digital Print | K113: 520819 | M113: 10.7 | N113: MTR | O113: 562 | P113: 0 | Q113: =M113*O113-P113 -> 6013.4 | R113: 0.05 | S113: CGST+SGST | T113: =IF(S113="IGST",ROUND(Q113*R113,2),0) -> 0 | U113: =IF(S113="CGST+SGST",ROUND(Q113*R113/2,2),0) -> 150.34 | V113: =U113 -> 150.34 | W113: 0 | X113: =Q113+T113+U113+V113+W113 -> 6314.08 | Y113: =ROUND(Q113*AT113,0) -> 0 | Z113: =X113-Y113 -> 6314.08 | AD113: Haryana (06) | AE113: 06AAFCN6567R1ZL | AF113: Haryana (06) | AG113: PO26000000830 | AH113: 46232 | AJ113: Replaces ND/26-27/043 dt 29-07-2026 (cancelled by CN ND/26-27/CN3) | AR113: No RCM – forward charge; goods, CGST 2.5% + SGST 2.5%. ITC eligible (check GSTR-2B). Re-issued to Haryana GSTIN – invoice says actual invoice date 29-07-2026. Original ND/26-27/043 (Delhi, IGST) cancelled by credit note ND/26-27/CN3 – not entered. PO no./date taken from email thread. Nicobar asked for LR copy for ₹650 freight. Terms 45 days. | AS113: Sec 393(1) – purchase of goods (old 194Q). Apply only if FY purchases from this supplier > ₹50 L – nil assumed. | AT113: 0
A114: 110 | B114: Niva's Designs\ND-26-27-043A 29.08.26.pdf | C114: ND/26-27/043A | D114: 46263 | E114: =YEAR(D114) -> 2026 | F114: =TEXT(D114,"mmm") -> Aug | G114: Niva's Designs | H114: 06BCAPS9611Q1Z0 | J114: Fabric – 25 Lee with Digital Print (White Strip) | K114: 520819 | M114: 6 | N114: MTR | O114: 1250 | P114: 0 | Q114: =M114*O114-P114 -> 7500 | R114: 0.05 | S114: CGST+SGST | T114: =IF(S114="IGST",ROUND(Q114*R114,2),0) -> 0 | U114: =IF(S114="CGST+SGST",ROUND(Q114*R114/2,2),0) -> 187.5 | V114: =U114 -> 187.5 | W114: 0 | X114: =Q114+T114+U114+V114+W114 -> 7875 | Y114: =ROUND(Q114*AT114,0) -> 0 | Z114: =X114-Y114 -> 7875 | AD114: Haryana (06) | AE114: 06AAFCN6567R1ZL | AF114: Haryana (06) | AG114: PO26000000830 | AH114: 46232 | AJ114: Replaces ND/26-27/043 dt 29-07-2026 (cancelled by CN ND/26-27/CN3) | AR114: No RCM – forward charge; goods, CGST 2.5% + SGST 2.5%. ITC eligible (check GSTR-2B). Re-issued to Haryana GSTIN – invoice says actual invoice date 29-07-2026. Original ND/26-27/043 (Delhi, IGST) cancelled by credit note ND/26-27/CN3 – not entered. PO no./date taken from email thread. Nicobar asked for LR copy for ₹650 freight. Terms 45 days. | AS114: Sec 393(1) – purchase of goods (old 194Q). Apply only if FY purchases from this supplier > ₹50 L – nil assumed. | AT114: 0
A115: 111 | B115: Niva's Designs\ND-26-27-043A 29.08.26.pdf | C115: ND/26-27/043A | D115: 46263 | E115: =YEAR(D115) -> 2026 | F115: =TEXT(D115,"mmm") -> Aug | G115: Niva's Designs | H115: 06BCAPS9611Q1Z0 | J115: Fabric – Cotton Duck with Digital Print | K115: 520819 | M115: 21.9 | N115: MTR | O115: 562 | P115: 0 | Q115: =M115*O115-P115 -> 12307.8 | R115: 0.05 | S115: CGST+SGST | T115: =IF(S115="IGST",ROUND(Q115*R115,2),0) -> 0 | U115: =IF(S115="CGST+SGST",ROUND(Q115*R115/2,2),0) -> 307.7 | V115: =U115 -> 307.7 | W115: 0 | X115: =Q115+T115+U115+V115+W115 -> 12923.2 | Y115: =ROUND(Q115*AT115,0) -> 0 | Z115: =X115-Y115 -> 12923.2 | AD115: Haryana (06) | AE115: 06AAFCN6567R1ZL | AF115: Haryana (06) | AG115: PO26000000830 | AH115: 46232 | AJ115: Replaces ND/26-27/043 dt 29-07-2026 (cancelled by CN ND/26-27/CN3) | AR115: No RCM – forward charge; goods, CGST 2.5% + SGST 2.5%. ITC eligible (check GSTR-2B). Re-issued to Haryana GSTIN – invoice says actual invoice date 29-07-2026. Original ND/26-27/043 (Delhi, IGST) cancelled by credit note ND/26-27/CN3 – not entered. PO no./date taken from email thread. Nicobar asked for LR copy for ₹650 freight. Terms 45 days. | AS115: Sec 393(1) – purchase of goods (old 194Q). Apply only if FY purchases from this supplier > ₹50 L – nil assumed. | AT115: 0
A116: 112 | B116: Niva's Designs\ND-26-27-043A 29.08.26.pdf | C116: ND/26-27/043A | D116: 46263 | E116: =YEAR(D116) -> 2026 | F116: =TEXT(D116,"mmm") -> Aug | G116: Niva's Designs | H116: 06BCAPS9611Q1Z0 | J116: Fabric – 10 Lee with Digital Print (Green Stripe) | K116: 520819 | M116: 5.9 | N116: MTR | O116: 1250 | P116: 0 | Q116: =M116*O116-P116 -> 7375 | R116: 0.05 | S116: CGST+SGST | T116: =IF(S116="IGST",ROUND(Q116*R116,2),0) -> 0 | U116: =IF(S116="CGST+SGST",ROUND(Q116*R116/2,2),0) -> 184.38 | V116: =U116 -> 184.38 | W116: 0 | X116: =Q116+T116+U116+V116+W116 -> 7743.76 | Y116: =ROUND(Q116*AT116,0) -> 0 | Z116: =X116-Y116 -> 7743.76 | AD116: Haryana (06) | AE116: 06AAFCN6567R1ZL | AF116: Haryana (06) | AG116: PO26000000830 | AH116: 46232 | AJ116: Replaces ND/26-27/043 dt 29-07-2026 (cancelled by CN ND/26-27/CN3) | AR116: No RCM – forward charge; goods, CGST 2.5% + SGST 2.5%. ITC eligible (check GSTR-2B). Re-issued to Haryana GSTIN – invoice says actual invoice date 29-07-2026. Original ND/26-27/043 (Delhi, IGST) cancelled by credit note ND/26-27/CN3 – not entered. PO no./date taken from email thread. Nicobar asked for LR copy for ₹650 freight. Terms 45 days. | AS116: Sec 393(1) – purchase of goods (old 194Q). Apply only if FY purchases from this supplier > ₹50 L – nil assumed. | AT116: 0
A117: 113 | B117: Niva's Designs\ND-26-27-043A 29.08.26.pdf | C117: ND/26-27/043A | D117: 46263 | E117: =YEAR(D117) -> 2026 | F117: =TEXT(D117,"mmm") -> Aug | G117: Niva's Designs | H117: 06BCAPS9611Q1Z0 | J117: Freight & forwarding charges | K117: 996511 | M117: 1 | N117: LOT | O117: 650 | P117: 0 | Q117: =M117*O117-P117 -> 650 | R117: 0.05 | S117: CGST+SGST | T117: =IF(S117="IGST",ROUND(Q117*R117,2),0) -> 0 | U117: =IF(S117="CGST+SGST",ROUND(Q117*R117/2,2),0) -> 16.25 | V117: =U117 -> 16.25 | W117: 0.46 | X117: =Q117+T117+U117+V117+W117 -> 682.96 | Y117: =ROUND(Q117*AT117,0) -> 0 | Z117: =X117-Y117 -> 682.96 | AD117: Haryana (06) | AE117: 06AAFCN6567R1ZL | AF117: Haryana (06) | AG117: PO26000000830 | AH117: 46232 | AJ117: Replaces ND/26-27/043 dt 29-07-2026 (cancelled by CN ND/26-27/CN3) | AR117: No RCM – forward charge; goods, CGST 2.5% + SGST 2.5%. ITC eligible (check GSTR-2B). Re-issued to Haryana GSTIN – invoice says actual invoice date 29-07-2026. Original ND/26-27/043 (Delhi, IGST) cancelled by credit note ND/26-27/CN3 – not entered. PO no./date taken from email thread. Nicobar asked for LR copy for ₹650 freight. Terms 45 days. | AS117: Sec 393(1) – purchase of goods (old 194Q). Apply only if FY purchases from this supplier > ₹50 L – nil assumed. | AT117: 0
A118: 114 | B118: Ambience Facilities Management Private Limited\CAF-10-34-26-27 01.10.26.pdf | C118: CAF/10/34/26-27 | D118: 46296 | E118: =YEAR(D118) -> 2026 | F118: =TEXT(D118,"mmm") -> Oct | G118: Ambience Facilities Management Private Limited | H118: 06AAICA8074F1ZM | J118: Common Area Maintenance charges – Shop G-20, Ambience Mall Gurugram – Oct-2026 | K118: 995419 | M118: 3145 | N118: SQFT | O118: 49 | P118: 0 | Q118: =M118*O118-P118 -> 154105 | R118: 0.18 | S118: CGST+SGST | T118: =IF(S118="IGST",ROUND(Q118*R118,2),0) -> 0 | U118: =IF(S118="CGST+SGST",ROUND(Q118*R118/2,2),0) -> 13869.45 | V118: =U118 -> 13869.45 | W118: 0.1 | X118: =Q118+T118+U118+V118+W118 -> 181844 | Y118: =ROUND(Q118*AT118,0) -> 3082 | Z118: =X118-Y118 -> 178762 | AD118: Haryana (06) | AE118: 06AAFCN6567R1ZL | AF118: Haryana (06) | AJ118: Shop G-20, Ambience Mall, Gurugram | AK118: 547d5661b70e3c82b732fcb558d32960d220e93278cc12d33b41974daa845bc7 | AL118: 132629077599798 | AM118: 2026-10-01 | AR118: No RCM – forward charge; CGST 9% + SGST 9% charged by supplier. ITC eligible (check GSTR-2B). Due 10-10-2026; 2% p.m. interest after due date. | AS118: Sec 393(1) – contract/service (old 194C), 2% (company). Confirm with CA. | AT118: 0.02
A119: 115 | B119: Ambience Developers & Infrastructure Pvt Ltd\SFE-09-32-26-27 30.09.26.pdf | C119: SFE/09/32/26-27 | D119: 46295 | E119: =YEAR(D119) -> 2026 | F119: =TEXT(D119,"mmm") -> Sep | G119: Ambience Developers & Infrastructure Pvt Ltd | H119: 06AAECA6894P1ZX | J119: Sinking fund charges towards electrical equipments & energy systems – Shop G-20 (Sep-2026) | K119: 996912 | M119: 2680 | N119: UNITS | O119: 4.3 | P119: 0 | Q119: =M119*O119-P119 -> 11524 | R119: 0.18 | S119: CGST+SGST | T119: =IF(S119="IGST",ROUND(Q119*R119,2),0) -> 0 | U119: =IF(S119="CGST+SGST",ROUND(Q119*R119/2,2),0) -> 1037.16 | V119: =U119 -> 1037.16 | W119: -0.32 | X119: =Q119+T119+U119+V119+W119 -> 13598 | Y119: =ROUND(Q119*AT119,0) -> 230 | Z119: =X119-Y119 -> 13368 | AD119: Haryana (06) | AE119: 06AAFCN6567R1ZL | AF119: Haryana (06) | AJ119: Shop G-20, Ambience Mall, Gurugram | AK119: 52a7ae08f2f01328ef0a2efdd61a86a54a884ca8e580106b06520a7ed669fa36 | AL119: 132629057383694 | AM119: 2026-09-30 | AR119: No RCM – forward charge; CGST 9% + SGST 9% charged by supplier. ITC eligible (check GSTR-2B). Due 09-10-2026. | AS119: Sec 393(1) – contract/service (old 194C), 2% (company). Confirm with CA. | AT119: 0.02
...

Sheet Emails Not Scanned
A1: Emails Not Scanned – invoice@nicobar.com
A2: Last Gmail scan: 01-10-2026 14:40 IST (window: 26-09-2026 21:59 IST to 01-10-2026 14:40 IST). Runs of 02-10-2026 10:41 IST, 03-10-2026 17:29 IST and 04-10-2026 09:13 IST could NOT scan Gmail (connector not attached) – window 01-10-2026 14:40 to 04-10-2026 09:13 IST still to be scanned. Emails below were not downloaded, or were scanned but their PDFs were not added to the register. The scheduled task retries "Not downloaded" emails each run.
A4: A. Not downloaded – PDFs NOT in the register (action needed)
A5: # | B5: Email Date (IST) | C5: From | D5: To | E5: Cc | F5: Subject | G5: Size (MB) | H5: Status | I5: Reason | J5: Action Needed | K5: Gmail Message ID | L5: Open in Gmail | M5: Last Attempt (IST)
A6: 1 | B6: 46289.48 | C6: rohitpundir@nicobar.com | D6: invoice@nicobar.com | F6: invoices | G6: 12.1 | H6: Not downloaded | I6: Download failed again on 01-10-2026 – the Gmail connection times out (session expired) on this very large email (~12.7 MB). It contains 12 PDFs: invoice_IN-2026-0408358, 2026-27194 - Nicobar Design Pvt Ltd, nico bar Sept, Niobar invoice, SHPL-PI-03-26-27, 2966091990_Nicobar_HVAC_20260801, 100107669 (4), Abode Inn- Invoice Jaipur, 2966091990_Nicobar_HVAC, Aug Sep 2026, LNKD_INVOICE_511294839131, maneet_invoice-nicobar. | J6: Save its PDFs into D:\Claude_Sales\Expenses (any subfolder) – the next run files them – or ask the sender to resend in smaller emails (under ~5 MB each). | K6: 1a0d201f04a25ddb | L6: Open email | M6: 46296.615
A7: 2 | B7: 46290.559 | C7: sanjaysharma@nicobar.com | D7: invoice@nicobar.com | E7: sachin@nicobar.com; shekharsingh@nicobar.com | F7: Invoices copy | G7: 13.8 | H7: Not downloaded | I7: Download failed again on 01-10-2026 – the Gmail connection times out (session expired) on this very large email (~14.5 MB). | J7: Save its PDFs into D:\Claude_Sales\Expenses, or ask the sender to resend in smaller emails. | K7: 1a0d7910bc5c3986 | L7: Open email | M7: 46296.615
A8: 3 | B8: 46289.683 | C8: prachisyal@nicobar.com | D8: invoice@nicobar.com | E8: sachin@nicobar.com | F8: scanned invoices | G8: 27.2 | H8: Not downloaded | I8: Too large to download (~28.6 MB) – emails of 12–14 MB still time out, so it was skipped again on 01-10-2026. | J8: Save its PDFs into D:\Claude_Sales\Expenses, or ask the sender to resend in smaller emails. | K8: 1a0d30cfb9b6e9da | L8: Open email | M8: 46296.615
A9: 4 | B9: 46289.728 | C9: prachisyal@nicobar.com | D9: invoice@nicobar.com | E9: sachin@nicobar.com | F9: Re: scanned invoices | G9: 18.6 | H9: Not downloaded | I9: Too large to download (~19.6 MB) – emails of 12–14 MB still time out, so it was skipped again on 01-10-2026. (The middle reply in this thread, 2.3 MB, WAS scanned: 12 DLF invoices + V Dine voucher added.) | J9: Save its PDFs into D:\Claude_Sales\Expenses, or ask the sender to resend in smaller emails. | K9: 1a0d348710f4c2a0 | L9: Open email | M9: 46296.615
A10: 5 | B10: — | C10: — (Gmail not read) | D10: invoice@nicobar.com | F10: Gmail not scanned – Gmail connector not attached to this scheduled task | H10: Not scanned | I10: Gmail not scanned on 02-10-2026, 03-10-2026 or 04-10-2026 – no Gmail tools were available to these runs (connector not attached to the scheduled task). Scan window NOT covered: 01-10-2026 14:40 IST to 04-10-2026 09:13 IST. The watermark was not advanced, so the next successful run will search this window. | J10: Re-attach the Gmail connector (with access to invoice@nicobar.com) to the scheduled task "Auto-add new invoices to Expense Register". | K10: — | M10: 2026-10-04 09:13
A12: B. Scanned – PDFs not added to the register (for information)
A13: # | B13: Email Date (IST) | C13: From | D13: To | E13: Cc | F13: Subject | G13: Size (MB) | H13: Status | I13: Reason | J13: Action Needed | K13: Gmail Message ID | L13: Open in Gmail | M13: Last Attempt (IST)
A14: 6 | B14: 46289.484 | C14: rohitpundir@nicobar.com | D14: invoice@nicobar.com | F14: Fwd: Electricity Bill | G14: 0.7 | H14: Scanned – not added | I14: Not billed to Nicobar: PSPCL electricity bill no. 50823959885 (a/c 3009140989) is in the name of Mr. Inderjeet Singh Dhillon; payable ₹24,947, due 21-Sep-2026. | J14: Pay/claim as landlord reimbursement if applicable; ask landlord for a GST invoice if needed. | K14: 1a0d206d9ab92844 | L14: Open email | M14: 46291.917
A15: 7 | B15: 46289.484 | C15: rohitpundir@nicobar.com | D15: invoice@nicobar.com | F15: Fwd: JCN Electricity Bill Payment Request for Aug-2026 | G15: 0.7 | H15: Scanned – not added | I15: Not billed to Nicobar: two Jaipur (JVVNL) electricity bills in the names of Rajeshwar Singh (₹35,646) and Narendra Kumari (₹22,459), due 22-Sep-2026. | J15: Same as above – landlord/individual bills. | K15: 1a0d206fd4b41ccc | L15: Open email | M15: 46291.917
A16: 8 | B16: 46289.484 | C16: rohitpundir@nicobar.com | D16: invoice@nicobar.com | F16: Fwd: PFA | G16: 0.4 | H16: Scanned – duplicate | I16: All 9 PDFs (Anthropic E87270F6-0001 to -0009) are already in the register (S.No. 23–31). | J16: None. | K16: 1a0d20671601042b | L16: Open email | M16: 46291.917
A17: 9 | B17: 46289.483 | C17: rohitpundir@nicobar.com | D17: invoice@nicobar.com | F17: Fwd: DPS BILL NMN | G17: 0.2 | H17: Scanned – duplicate | I17: DPS Telecom 09-UPTIN26003027 is already in the register (S.No. 14). | J17: None. | K17: 1a0d205577740520 | L17: Open email | M17: 46291.917
A18: 10 | B18: 46289.484 | C18: rohitpundir@nicobar.com | D18: invoice@nicobar.com | F18: Fwd: Invoices | G18: 0.7 | H18: Scanned – duplicate | I18: All 3 Vraj Commercial invoices (CH/0562, EL-DG/0545, Rent/0613) are already in the register (S.No. 15–22). | J18: None. | K18: 1a0d2069e10849b4 | L18: Open email | M18: 46291.917
A19: 11 | B19: 46289.72 | C19: himanshu@nicobar.com | D19: invoice@nicobar.com | F19: Fwd: FW: DTDC Freight Invoice For The Month Of Aug-26 (NICOBAR DESIGN PRIVATE LIMITED) | G19: 1.2 | H19: Scanned – duplicate | I19: Second copy of the same 14 DTDC PDFs; the first email in the thread was added. | J19: None. | K19: 1a0d33e26521b364 | L19: Open email | M19: 46291.917
A20: 12 | B20: 46290.459 | C20: rohitpundir@nicobar.com | D20: invoice@nicobar.com | F20: Fwd: Payout | Surbhi Sethi | Sept | G20: 2.6 | H20: Scanned – partly added | I20: Invoice 013/2026-27 was added. The other 2 PDFs (GST registration certificate, cancelled cheque + PAN) are supporting documents, not invoices. | J20: None. | K20: 1a0d70bed2fc365a | L20: Open email | M20: 46291.917
A21: 13 | B21: 46289.721 | C21: himanshu@nicobar.com | D21: invoice@nicobar.com | F21: Fwd: FW: Blue Dart Invoice for month of AUGUST 2026 - FAR322055 | G21: 3.4 | H21: Scanned – partly added | I21: 7 invoices were added. The "CovReport" PDF is a statement/cover summary (total ₹58,559.18), not an invoice. | J21: None. | K21: 1a0d33e6fd2816a4 | L21: Open email | M21: 46291.917
A22: 14 | B22: 46296.609 | C22: sachin@nicobar.com (fwd from Mohit Jaiswal) | D22: invoice@nicobar.com | F22: FW: Monthly closing Sep26 | G22: 0.13 | H22: Scanned – not added | I22: Not billed to Nicobar: IPinfo Inc. invoice 3MNDSIX0-0003 dated 06-06-2026 (US$481.40) is billed to "Shashi Kapoor" (an individual), not Nicobar Design Pvt Ltd. | J22: Ask IPinfo to reissue the invoice in Nicobar Design Pvt Ltd name (with GSTIN) if it is to be booked; otherwise save it into D:\Claude_Sales\Expenses and confirm. | K22: 1a0f6b74723eef83 | L22: Open email | M22: 46296.615
A23: 15 | B23: 46296.609 | C23: sachin@nicobar.com (fwd from Archana Roy) | D23: invoice@nicobar.com | F23: FW: NICOBAR DEAL @ JUHU BROKERAGE FEE CONFIRMATION | G23: 0.27 | H23: Scanned – duplicate | I23: Earlier copy of Cushman & Wakefield invoice MH-2026-09-2376 (Lower Parel bill-to address); same invoice no. and IRN as the revised invoice that WAS added from the 01-10-2026 email. | J23: None. | K23: 1a0f6b798b0b622f | L23: Open email | M23: 46296.615
A24: 16 | B24: 46296.607 | C24: sachin@nicobar.com (fwd from MKR APP) | D24: invoice@nicobar.com | F24: FW: Request for Account Statement – April 2026 to Date | G24: 0.38 | H24: Scanned – not added | I24: GL_26-27.pdf is an account statement, not an invoice. MKR says invoices MKR/26-27/8 (15-07-2026) and MKR/26-27/12 (15-09-2026) are not in Nicobar records – neither invoice PDF was attached. | J24: Ask MKR APP (P) Ltd for copies of MKR/26-27/8 and /12 and save them into D:\Claude_Sales\Expenses. | K24: 1a0f6b4c4a7b2435 | L24: Open email | M24: 46296.615
A25: 17 | B25: 46296.609 | C25: sachin@nicobar.com (fwd from Niva's Designs) | D25: invoice@nicobar.com | F25: FW: RE: NIVAS DESIGNS_Outstanding Payments as on 10-06-2026 | G25: 2.1 | H25: Scanned – partly added | I25: Invoice ND/26-27/043A (Haryana, ₹35,539) was added. ND/26-27/043 dated 29-07-2026 (Delhi, IGST) was not added because credit note ND/26-27/CN3 cancels it (credit notes are not entered). | J25: None. | K25: 1a0f6b78bc5359c3 | L25: Open email | M25: 46296.615
